[
  {
    "request_num": 1,
    "payload":     "100kb.bin",
    "attempt":     1,
    "protocol":    "QUIC/HTTP3",
    "size_bytes":  102459,
    "time_connect_s":  0.000460,
    "time_ttfb_s":     0.000270,
    "time_ttlb_s":     0.000360,
    "time_total_s":    0.003,
    "speed_Bps":  40545706,
    "speed_KBps": 39595.416,
    "speed_MBps": 38.667
  }
,
  {
    "request_num": 2,
    "payload":     "100kb.bin",
    "attempt":     2,
    "protocol":    "QUIC/HTTP3",
    "size_bytes":  102459,
    "time_connect_s":  0.000460,
    "time_ttfb_s":     0.000270,
    "time_ttlb_s":     0.000410,
    "time_total_s":    0.002,
    "speed_Bps":  41280822,
    "speed_KBps": 40313.303,
    "speed_MBps": 39.368
  }
,
  {
    "request_num": 3,
    "payload":     "100kb.bin",
    "attempt":     3,
    "protocol":    "QUIC/HTTP3",
    "size_bytes":  102459,
    "time_connect_s":  0.000450,
    "time_ttfb_s":     0.000270,
    "time_ttlb_s":     0.000360,
    "time_total_s":    0.002,
    "speed_Bps":  42112207,
    "speed_KBps": 41125.202,
    "speed_MBps": 40.161
  }
,
  {
    "request_num": 4,
    "payload":     "100kb.bin",
    "attempt":     4,
    "protocol":    "QUIC/HTTP3",
    "size_bytes":  102459,
    "time_connect_s":  0.000460,
    "time_ttfb_s":     0.000270,
    "time_ttlb_s":     0.000410,
    "time_total_s":    0.002,
    "speed_Bps":  42077618,
    "speed_KBps": 41091.424,
    "speed_MBps": 40.128
  }
,
  {
    "request_num": 5,
    "payload":     "100kb.bin",
    "attempt":     5,
    "protocol":    "QUIC/HTTP3",
    "size_bytes":  102459,
    "time_connect_s":  0.000450,
    "time_ttfb_s":     0.000420,
    "time_ttlb_s":     0.000340,
    "time_total_s":    0.003,
    "speed_Bps":  40529668,
    "speed_KBps": 39579.754,
    "speed_MBps": 38.652
  }
,
  {
    "request_num": 6,
    "payload":     "100kb.bin",
    "attempt":     6,
    "protocol":    "QUIC/HTTP3",
    "size_bytes":  102459,
    "time_connect_s":  0.000450,
    "time_ttfb_s":     0.000280,
    "time_ttlb_s":     0.000380,
    "time_total_s":    0.003,
    "speed_Bps":  40787818,
    "speed_KBps": 39831.854,
    "speed_MBps": 38.898
  }
,
  {
    "request_num": 7,
    "payload":     "100kb.bin",
    "attempt":     7,
    "protocol":    "QUIC/HTTP3",
    "size_bytes":  102459,
    "time_connect_s":  0.000450,
    "time_ttfb_s":     0.000260,
    "time_ttlb_s":     0.000380,
    "time_total_s":    0.002,
    "speed_Bps":  42268564,
    "speed_KBps": 41277.895,
    "speed_MBps": 40.310
  }
,
  {
    "request_num": 8,
    "payload":     "100kb.bin",
    "attempt":     8,
    "protocol":    "QUIC/HTTP3",
    "size_bytes":  102459,
    "time_connect_s":  0.000410,
    "time_ttfb_s":     0.000320,
    "time_ttlb_s":     0.000260,
    "time_total_s":    0.002,
    "speed_Bps":  44335353,
    "speed_KBps": 43296.243,
    "speed_MBps": 42.281
  }
,
  {
    "request_num": 9,
    "payload":     "100kb.bin",
    "attempt":     9,
    "protocol":    "QUIC/HTTP3",
    "size_bytes":  102459,
    "time_connect_s":  0.000450,
    "time_ttfb_s":     0.000270,
    "time_ttlb_s":     0.000320,
    "time_total_s":    0.002,
    "speed_Bps":  43917274,
    "speed_KBps": 42887.963,
    "speed_MBps": 41.883
  }
,
  {
    "request_num": 10,
    "payload":     "100kb.bin",
    "attempt":     10,
    "protocol":    "QUIC/HTTP3",
    "size_bytes":  102459,
    "time_connect_s":  0.000410,
    "time_ttfb_s":     0.000310,
    "time_ttlb_s":     0.000270,
    "time_total_s":    0.002,
    "speed_Bps":  44431483,
    "speed_KBps": 43390.120,
    "speed_MBps": 42.373
  }
,
  {
    "request_num": 11,
    "payload":     "100kb.bin",
    "attempt":     11,
    "protocol":    "QUIC/HTTP3",
    "size_bytes":  102459,
    "time_connect_s":  0.000410,
    "time_ttfb_s":     0.000330,
    "time_ttlb_s":     0.000260,
    "time_total_s":    0.002,
    "speed_Bps":  43249894,
    "speed_KBps": 42236.225,
    "speed_MBps": 41.246
  }
,
  {
    "request_num": 12,
    "payload":     "100kb.bin",
    "attempt":     12,
    "protocol":    "QUIC/HTTP3",
    "size_bytes":  102459,
    "time_connect_s":  0.000430,
    "time_ttfb_s":     0.000320,
    "time_ttlb_s":     0.000270,
    "time_total_s":    0.002,
    "speed_Bps":  43488540,
    "speed_KBps": 42469.277,
    "speed_MBps": 41.474
  }
,
  {
    "request_num": 13,
    "payload":     "100kb.bin",
    "attempt":     13,
    "protocol":    "QUIC/HTTP3",
    "size_bytes":  102459,
    "time_connect_s":  0.000410,
    "time_ttfb_s":     0.000320,
    "time_ttlb_s":     0.000260,
    "time_total_s":    0.002,
    "speed_Bps":  45076551,
    "speed_KBps": 44020.069,
    "speed_MBps": 42.988
  }
,
  {
    "request_num": 14,
    "payload":     "100kb.bin",
    "attempt":     14,
    "protocol":    "QUIC/HTTP3",
    "size_bytes":  102459,
    "time_connect_s":  0.000450,
    "time_ttfb_s":     0.000250,
    "time_ttlb_s":     0.000400,
    "time_total_s":    0.002,
    "speed_Bps":  42181556,
    "speed_KBps": 41192.926,
    "speed_MBps": 40.227
  }
,
  {
    "request_num": 15,
    "payload":     "100kb.bin",
    "attempt":     15,
    "protocol":    "QUIC/HTTP3",
    "size_bytes":  102459,
    "time_connect_s":  0.000430,
    "time_ttfb_s":     0.000310,
    "time_ttlb_s":     0.000250,
    "time_total_s":    0.002,
    "speed_Bps":  44011598,
    "speed_KBps": 42980.076,
    "speed_MBps": 41.973
  }
,
  {
    "request_num": 16,
    "payload":     "100kb.bin",
    "attempt":     16,
    "protocol":    "QUIC/HTTP3",
    "size_bytes":  102459,
    "time_connect_s":  0.000450,
    "time_ttfb_s":     0.000300,
    "time_ttlb_s":     0.000230,
    "time_total_s":    0.002,
    "speed_Bps":  45036923,
    "speed_KBps": 43981.370,
    "speed_MBps": 42.951
  }
,
  {
    "request_num": 17,
    "payload":     "100kb.bin",
    "attempt":     17,
    "protocol":    "QUIC/HTTP3",
    "size_bytes":  102459,
    "time_connect_s":  0.000440,
    "time_ttfb_s":     0.000270,
    "time_ttlb_s":     0.000360,
    "time_total_s":    0.002,
    "speed_Bps":  42744681,
    "speed_KBps": 41742.853,
    "speed_MBps": 40.765
  }
,
  {
    "request_num": 18,
    "payload":     "100kb.bin",
    "attempt":     18,
    "protocol":    "QUIC/HTTP3",
    "size_bytes":  102459,
    "time_connect_s":  0.000490,
    "time_ttfb_s":     0.000340,
    "time_ttlb_s":     0.000270,
    "time_total_s":    0.003,
    "speed_Bps":  40306452,
    "speed_KBps": 39361.770,
    "speed_MBps": 38.439
  }
,
  {
    "request_num": 19,
    "payload":     "100kb.bin",
    "attempt":     19,
    "protocol":    "QUIC/HTTP3",
    "size_bytes":  102459,
    "time_connect_s":  0.000430,
    "time_ttfb_s":     0.000260,
    "time_ttlb_s":     0.000330,
    "time_total_s":    0.002,
    "speed_Bps":  43031919,
    "speed_KBps": 42023.358,
    "speed_MBps": 41.038
  }
,
  {
    "request_num": 20,
    "payload":     "100kb.bin",
    "attempt":     20,
    "protocol":    "QUIC/HTTP3",
    "size_bytes":  102459,
    "time_connect_s":  0.000450,
    "time_ttfb_s":     0.000260,
    "time_ttlb_s":     0.000400,
    "time_total_s":    0.002,
    "speed_Bps":  42286009,
    "speed_KBps": 41294.931,
    "speed_MBps": 40.327
  }
,
  {
    "request_num": 21,
    "payload":     "100kb.bin",
    "attempt":     21,
    "protocol":    "QUIC/HTTP3",
    "size_bytes":  102459,
    "time_connect_s":  0.000440,
    "time_ttfb_s":     0.000250,
    "time_ttlb_s":     0.000420,
    "time_total_s":    0.002,
    "speed_Bps":  42655704,
    "speed_KBps": 41655.961,
    "speed_MBps": 40.680
  }
,
  {
    "request_num": 22,
    "payload":     "100kb.bin",
    "attempt":     22,
    "protocol":    "QUIC/HTTP3",
    "size_bytes":  102459,
    "time_connect_s":  0.000440,
    "time_ttfb_s":     0.000390,
    "time_ttlb_s":     0.000330,
    "time_total_s":    0.002,
    "speed_Bps":  41431055,
    "speed_KBps": 40460.015,
    "speed_MBps": 39.512
  }
,
  {
    "request_num": 23,
    "payload":     "100kb.bin",
    "attempt":     23,
    "protocol":    "QUIC/HTTP3",
    "size_bytes":  102459,
    "time_connect_s":  0.000560,
    "time_ttfb_s":     0.000300,
    "time_ttlb_s":     0.000270,
    "time_total_s":    0.002,
    "speed_Bps":  42129523,
    "speed_KBps": 41142.112,
    "speed_MBps": 40.178
  }
,
  {
    "request_num": 24,
    "payload":     "100kb.bin",
    "attempt":     24,
    "protocol":    "QUIC/HTTP3",
    "size_bytes":  102459,
    "time_connect_s":  0.000450,
    "time_ttfb_s":     0.000280,
    "time_ttlb_s":     0.000350,
    "time_total_s":    0.002,
    "speed_Bps":  42887819,
    "speed_KBps": 41882.636,
    "speed_MBps": 40.901
  }
,
  {
    "request_num": 25,
    "payload":     "100kb.bin",
    "attempt":     25,
    "protocol":    "QUIC/HTTP3",
    "size_bytes":  102459,
    "time_connect_s":  0.000450,
    "time_ttfb_s":     0.000280,
    "time_ttlb_s":     0.000340,
    "time_total_s":    0.002,
    "speed_Bps":  42834030,
    "speed_KBps": 41830.107,
    "speed_MBps": 40.850
  }
,
  {
    "request_num": 26,
    "payload":     "100kb.bin",
    "attempt":     26,
    "protocol":    "QUIC/HTTP3",
    "size_bytes":  102459,
    "time_connect_s":  0.000450,
    "time_ttfb_s":     0.000270,
    "time_ttlb_s":     0.000390,
    "time_total_s":    0.002,
    "speed_Bps":  42426087,
    "speed_KBps": 41431.726,
    "speed_MBps": 40.461
  }
,
  {
    "request_num": 27,
    "payload":     "100kb.bin",
    "attempt":     27,
    "protocol":    "QUIC/HTTP3",
    "size_bytes":  102459,
    "time_connect_s":  0.000440,
    "time_ttfb_s":     0.000350,
    "time_ttlb_s":     0.000280,
    "time_total_s":    0.002,
    "speed_Bps":  43451654,
    "speed_KBps": 42433.256,
    "speed_MBps": 41.439
  }
,
  {
    "request_num": 28,
    "payload":     "100kb.bin",
    "attempt":     28,
    "protocol":    "QUIC/HTTP3",
    "size_bytes":  102459,
    "time_connect_s":  0.000430,
    "time_ttfb_s":     0.000350,
    "time_ttlb_s":     0.000280,
    "time_total_s":    0.002,
    "speed_Bps":  42905779,
    "speed_KBps": 41900.175,
    "speed_MBps": 40.918
  }
,
  {
    "request_num": 29,
    "payload":     "100kb.bin",
    "attempt":     29,
    "protocol":    "QUIC/HTTP3",
    "size_bytes":  102459,
    "time_connect_s":  0.000420,
    "time_ttfb_s":     0.000310,
    "time_ttlb_s":     0.000250,
    "time_total_s":    0.002,
    "speed_Bps":  44879106,
    "speed_KBps": 43827.252,
    "speed_MBps": 42.800
  }
,
  {
    "request_num": 30,
    "payload":     "100kb.bin",
    "attempt":     30,
    "protocol":    "QUIC/HTTP3",
    "size_bytes":  102459,
    "time_connect_s":  0.000410,
    "time_ttfb_s":     0.000240,
    "time_ttlb_s":     0.000220,
    "time_total_s":    0.002,
    "speed_Bps":  46806304,
    "speed_KBps": 45709.281,
    "speed_MBps": 44.638
  }
,
  {
    "request_num": 31,
    "payload":     "100kb.bin",
    "attempt":     31,
    "protocol":    "QUIC/HTTP3",
    "size_bytes":  102459,
    "time_connect_s":  0.000450,
    "time_ttfb_s":     0.000260,
    "time_ttlb_s":     0.000380,
    "time_total_s":    0.002,
    "speed_Bps":  42390981,
    "speed_KBps": 41397.442,
    "speed_MBps": 40.427
  }
,
  {
    "request_num": 32,
    "payload":     "100kb.bin",
    "attempt":     32,
    "protocol":    "QUIC/HTTP3",
    "size_bytes":  102459,
    "time_connect_s":  0.000420,
    "time_ttfb_s":     0.000350,
    "time_ttlb_s":     0.000250,
    "time_total_s":    0.002,
    "speed_Bps":  44144334,
    "speed_KBps": 43109.701,
    "speed_MBps": 42.099
  }
,
  {
    "request_num": 33,
    "payload":     "100kb.bin",
    "attempt":     33,
    "protocol":    "QUIC/HTTP3",
    "size_bytes":  102459,
    "time_connect_s":  0.000400,
    "time_ttfb_s":     0.000300,
    "time_ttlb_s":     0.000240,
    "time_total_s":    0.002,
    "speed_Bps":  45904570,
    "speed_KBps": 44828.682,
    "speed_MBps": 43.778
  }
,
  {
    "request_num": 34,
    "payload":     "100kb.bin",
    "attempt":     34,
    "protocol":    "QUIC/HTTP3",
    "size_bytes":  102459,
    "time_connect_s":  0.000450,
    "time_ttfb_s":     0.000280,
    "time_ttlb_s":     0.000390,
    "time_total_s":    0.002,
    "speed_Bps":  42584788,
    "speed_KBps": 41586.707,
    "speed_MBps": 40.612
  }
,
  {
    "request_num": 35,
    "payload":     "100kb.bin",
    "attempt":     35,
    "protocol":    "QUIC/HTTP3",
    "size_bytes":  102459,
    "time_connect_s":  0.000420,
    "time_ttfb_s":     0.000260,
    "time_ttlb_s":     0.000390,
    "time_total_s":    0.002,
    "speed_Bps":  43488540,
    "speed_KBps": 42469.277,
    "speed_MBps": 41.474
  }
,
  {
    "request_num": 36,
    "payload":     "100kb.bin",
    "attempt":     36,
    "protocol":    "QUIC/HTTP3",
    "size_bytes":  102459,
    "time_connect_s":  0.000430,
    "time_ttfb_s":     0.000250,
    "time_ttlb_s":     0.000390,
    "time_total_s":    0.002,
    "speed_Bps":  43140632,
    "speed_KBps": 42129.523,
    "speed_MBps": 41.142
  }
,
  {
    "request_num": 37,
    "payload":     "100kb.bin",
    "attempt":     37,
    "protocol":    "QUIC/HTTP3",
    "size_bytes":  102459,
    "time_connect_s":  0.000440,
    "time_ttfb_s":     0.000250,
    "time_ttlb_s":     0.000370,
    "time_total_s":    0.002,
    "speed_Bps":  43581029,
    "speed_KBps": 42559.599,
    "speed_MBps": 41.562
  }
,
  {
    "request_num": 38,
    "payload":     "100kb.bin",
    "attempt":     38,
    "protocol":    "QUIC/HTTP3",
    "size_bytes":  102459,
    "time_connect_s":  0.000420,
    "time_ttfb_s":     0.000340,
    "time_ttlb_s":     0.000270,
    "time_total_s":    0.002,
    "speed_Bps":  44239637,
    "speed_KBps": 43202.771,
    "speed_MBps": 42.190
  }
,
  {
    "request_num": 39,
    "payload":     "100kb.bin",
    "attempt":     39,
    "protocol":    "QUIC/HTTP3",
    "size_bytes":  102459,
    "time_connect_s":  0.000440,
    "time_ttfb_s":     0.000270,
    "time_ttlb_s":     0.000390,
    "time_total_s":    0.002,
    "speed_Bps":  42025841,
    "speed_KBps": 41040.860,
    "speed_MBps": 40.079
  }
,
  {
    "request_num": 40,
    "payload":     "100kb.bin",
    "attempt":     40,
    "protocol":    "QUIC/HTTP3",
    "size_bytes":  102459,
    "time_connect_s":  0.000480,
    "time_ttfb_s":     0.000280,
    "time_ttlb_s":     0.000410,
    "time_total_s":    0.002,
    "speed_Bps":  41633076,
    "speed_KBps": 40657.301,
    "speed_MBps": 39.704
  }
,
  {
    "request_num": 41,
    "payload":     "1mb.bin",
    "attempt":     1,
    "protocol":    "QUIC/HTTP3",
    "size_bytes":  1048635,
    "time_connect_s":  0.000440,
    "time_ttfb_s":     0.000780,
    "time_ttlb_s":     0.004040,
    "time_total_s":    0.007,
    "speed_Bps":  158619725,
    "speed_KBps": 154902.075,
    "speed_MBps": 151.272
  }
,
  {
    "request_num": 42,
    "payload":     "1mb.bin",
    "attempt":     2,
    "protocol":    "QUIC/HTTP3",
    "size_bytes":  1048635,
    "time_connect_s":  0.000440,
    "time_ttfb_s":     0.000400,
    "time_ttlb_s":     0.003410,
    "time_total_s":    0.006,
    "speed_Bps":  187457097,
    "speed_KBps": 183063.571,
    "speed_MBps": 178.773
  }
,
  {
    "request_num": 43,
    "payload":     "1mb.bin",
    "attempt":     3,
    "protocol":    "QUIC/HTTP3",
    "size_bytes":  1048635,
    "time_connect_s":  0.000460,
    "time_ttfb_s":     0.000260,
    "time_ttlb_s":     0.003160,
    "time_total_s":    0.005,
    "speed_Bps":  200964929,
    "speed_KBps": 196254.813,
    "speed_MBps": 191.655
  }
,
  {
    "request_num": 44,
    "payload":     "1mb.bin",
    "attempt":     4,
    "protocol":    "QUIC/HTTP3",
    "size_bytes":  1048635,
    "time_connect_s":  0.000410,
    "time_ttfb_s":     0.000340,
    "time_ttlb_s":     0.003310,
    "time_total_s":    0.005,
    "speed_Bps":  191321839,
    "speed_KBps": 186837.733,
    "speed_MBps": 182.459
  }
,
  {
    "request_num": 45,
    "payload":     "1mb.bin",
    "attempt":     5,
    "protocol":    "QUIC/HTTP3",
    "size_bytes":  1048635,
    "time_connect_s":  0.000420,
    "time_ttfb_s":     0.000340,
    "time_ttlb_s":     0.003140,
    "time_total_s":    0.005,
    "speed_Bps":  200159382,
    "speed_KBps": 195468.146,
    "speed_MBps": 190.887
  }
,
  {
    "request_num": 46,
    "payload":     "1mb.bin",
    "attempt":     6,
    "protocol":    "QUIC/HTTP3",
    "size_bytes":  1048635,
    "time_connect_s":  0.000520,
    "time_ttfb_s":     0.000270,
    "time_ttlb_s":     0.003730,
    "time_total_s":    0.006,
    "speed_Bps":  178947952,
    "speed_KBps": 174753.859,
    "speed_MBps": 170.658
  }
,
  {
    "request_num": 47,
    "payload":     "1mb.bin",
    "attempt":     7,
    "protocol":    "QUIC/HTTP3",
    "size_bytes":  1048635,
    "time_connect_s":  0.000450,
    "time_ttfb_s":     0.000270,
    "time_ttlb_s":     0.003360,
    "time_total_s":    0.005,
    "speed_Bps":  192128069,
    "speed_KBps": 187625.067,
    "speed_MBps": 183.228
  }
,
  {
    "request_num": 48,
    "payload":     "1mb.bin",
    "attempt":     8,
    "protocol":    "QUIC/HTTP3",
    "size_bytes":  1048635,
    "time_connect_s":  0.000440,
    "time_ttfb_s":     0.000240,
    "time_ttlb_s":     0.003580,
    "time_total_s":    0.006,
    "speed_Bps":  188603417,
    "speed_KBps": 184183.024,
    "speed_MBps": 179.866
  }
,
  {
    "request_num": 49,
    "payload":     "1mb.bin",
    "attempt":     9,
    "protocol":    "QUIC/HTTP3",
    "size_bytes":  1048635,
    "time_connect_s":  0.000450,
    "time_ttfb_s":     0.000390,
    "time_ttlb_s":     0.003470,
    "time_total_s":    0.006,
    "speed_Bps":  185467810,
    "speed_KBps": 181120.908,
    "speed_MBps": 176.876
  }
,
  {
    "request_num": 50,
    "payload":     "1mb.bin",
    "attempt":     10,
    "protocol":    "QUIC/HTTP3",
    "size_bytes":  1048635,
    "time_connect_s":  0.000450,
    "time_ttfb_s":     0.000270,
    "time_ttlb_s":     0.003850,
    "time_total_s":    0.006,
    "speed_Bps":  177915677,
    "speed_KBps": 173745.778,
    "speed_MBps": 169.674
  }
,
  {
    "request_num": 51,
    "payload":     "1mb.bin",
    "attempt":     11,
    "protocol":    "QUIC/HTTP3",
    "size_bytes":  1048635,
    "time_connect_s":  0.000460,
    "time_ttfb_s":     0.000260,
    "time_ttlb_s":     0.003570,
    "time_total_s":    0.006,
    "speed_Bps":  188298617,
    "speed_KBps": 183885.368,
    "speed_MBps": 179.576
  }
,
  {
    "request_num": 52,
    "payload":     "1mb.bin",
    "attempt":     12,
    "protocol":    "QUIC/HTTP3",
    "size_bytes":  1048635,
    "time_connect_s":  0.000420,
    "time_ttfb_s":     0.000320,
    "time_ttlb_s":     0.002580,
    "time_total_s":    0.005,
    "speed_Bps":  227617756,
    "speed_KBps": 222282.965,
    "speed_MBps": 217.073
  }
,
  {
    "request_num": 53,
    "payload":     "1mb.bin",
    "attempt":     13,
    "protocol":    "QUIC/HTTP3",
    "size_bytes":  1048635,
    "time_connect_s":  0.000410,
    "time_ttfb_s":     0.000270,
    "time_ttlb_s":     0.003620,
    "time_total_s":    0.006,
    "speed_Bps":  184456464,
    "speed_KBps": 180133.266,
    "speed_MBps": 175.911
  }
,
  {
    "request_num": 54,
    "payload":     "1mb.bin",
    "attempt":     14,
    "protocol":    "QUIC/HTTP3",
    "size_bytes":  1048635,
    "time_connect_s":  0.000420,
    "time_ttfb_s":     0.000330,
    "time_ttlb_s":     0.003110,
    "time_total_s":    0.005,
    "speed_Bps":  202322014,
    "speed_KBps": 197580.092,
    "speed_MBps": 192.949
  }
,
  {
    "request_num": 55,
    "payload":     "1mb.bin",
    "attempt":     15,
    "protocol":    "QUIC/HTTP3",
    "size_bytes":  1048635,
    "time_connect_s":  0.000470,
    "time_ttfb_s":     0.000260,
    "time_ttlb_s":     0.003180,
    "time_total_s":    0.005,
    "speed_Bps":  200618902,
    "speed_KBps": 195916.896,
    "speed_MBps": 191.325
  }
,
  {
    "request_num": 56,
    "payload":     "1mb.bin",
    "attempt":     16,
    "protocol":    "QUIC/HTTP3",
    "size_bytes":  1048635,
    "time_connect_s":  0.000450,
    "time_ttfb_s":     0.000260,
    "time_ttlb_s":     0.003720,
    "time_total_s":    0.006,
    "speed_Bps":  182403027,
    "speed_KBps": 178127.956,
    "speed_MBps": 173.953
  }
,
  {
    "request_num": 57,
    "payload":     "1mb.bin",
    "attempt":     17,
    "protocol":    "QUIC/HTTP3",
    "size_bytes":  1048635,
    "time_connect_s":  0.000480,
    "time_ttfb_s":     0.000280,
    "time_ttlb_s":     0.003390,
    "time_total_s":    0.005,
    "speed_Bps":  192586777,
    "speed_KBps": 188073.024,
    "speed_MBps": 183.665
  }
,
  {
    "request_num": 58,
    "payload":     "1mb.bin",
    "attempt":     18,
    "protocol":    "QUIC/HTTP3",
    "size_bytes":  1048635,
    "time_connect_s":  0.000440,
    "time_ttfb_s":     0.000260,
    "time_ttlb_s":     0.003510,
    "time_total_s":    0.006,
    "speed_Bps":  189215987,
    "speed_KBps": 184781.237,
    "speed_MBps": 180.450
  }
,
  {
    "request_num": 59,
    "payload":     "1mb.bin",
    "attempt":     19,
    "protocol":    "QUIC/HTTP3",
    "size_bytes":  1048635,
    "time_connect_s":  0.000450,
    "time_ttfb_s":     0.000260,
    "time_ttlb_s":     0.003470,
    "time_total_s":    0.006,
    "speed_Bps":  190591603,
    "speed_KBps": 186124.612,
    "speed_MBps": 181.762
  }
,
  {
    "request_num": 60,
    "payload":     "1mb.bin",
    "attempt":     20,
    "protocol":    "QUIC/HTTP3",
    "size_bytes":  1048635,
    "time_connect_s":  0.000450,
    "time_ttfb_s":     0.000260,
    "time_ttlb_s":     0.003710,
    "time_total_s":    0.006,
    "speed_Bps":  182657203,
    "speed_KBps": 178376.175,
    "speed_MBps": 174.195
  }
,
  {
    "request_num": 61,
    "payload":     "1mb.bin",
    "attempt":     21,
    "protocol":    "QUIC/HTTP3",
    "size_bytes":  1048635,
    "time_connect_s":  0.000450,
    "time_ttfb_s":     0.000260,
    "time_ttlb_s":     0.003530,
    "time_total_s":    0.006,
    "speed_Bps":  187256250,
    "speed_KBps": 182867.432,
    "speed_MBps": 178.581
  }
,
  {
    "request_num": 62,
    "payload":     "1mb.bin",
    "attempt":     22,
    "protocol":    "QUIC/HTTP3",
    "size_bytes":  1048635,
    "time_connect_s":  0.000410,
    "time_ttfb_s":     0.000250,
    "time_ttlb_s":     0.003740,
    "time_total_s":    0.006,
    "speed_Bps":  180581195,
    "speed_KBps": 176348.823,
    "speed_MBps": 172.216
  }
,
  {
    "request_num": 63,
    "payload":     "1mb.bin",
    "attempt":     23,
    "protocol":    "QUIC/HTTP3",
    "size_bytes":  1048635,
    "time_connect_s":  0.000450,
    "time_ttfb_s":     0.000240,
    "time_ttlb_s":     0.002990,
    "time_total_s":    0.005,
    "speed_Bps":  209894916,
    "speed_KBps": 204975.504,
    "speed_MBps": 200.171
  }
,
  {
    "request_num": 64,
    "payload":     "1mb.bin",
    "attempt":     24,
    "protocol":    "QUIC/HTTP3",
    "size_bytes":  1048635,
    "time_connect_s":  0.000460,
    "time_ttfb_s":     0.000270,
    "time_ttlb_s":     0.003550,
    "time_total_s":    0.006,
    "speed_Bps":  186855845,
    "speed_KBps": 182476.411,
    "speed_MBps": 178.200
  }
,
  {
    "request_num": 65,
    "payload":     "1mb.bin",
    "attempt":     25,
    "protocol":    "QUIC/HTTP3",
    "size_bytes":  1048635,
    "time_connect_s":  0.000430,
    "time_ttfb_s":     0.000280,
    "time_ttlb_s":     0.003270,
    "time_total_s":    0.005,
    "speed_Bps":  199133118,
    "speed_KBps": 194465.936,
    "speed_MBps": 189.908
  }
,
  {
    "request_num": 66,
    "payload":     "1mb.bin",
    "attempt":     26,
    "protocol":    "QUIC/HTTP3",
    "size_bytes":  1048635,
    "time_connect_s":  0.000460,
    "time_ttfb_s":     0.000280,
    "time_ttlb_s":     0.003020,
    "time_total_s":    0.005,
    "speed_Bps":  206994670,
    "speed_KBps": 202143.232,
    "speed_MBps": 197.406
  }
,
  {
    "request_num": 67,
    "payload":     "1mb.bin",
    "attempt":     27,
    "protocol":    "QUIC/HTTP3",
    "size_bytes":  1048635,
    "time_connect_s":  0.000460,
    "time_ttfb_s":     0.000260,
    "time_ttlb_s":     0.003570,
    "time_total_s":    0.006,
    "speed_Bps":  186855845,
    "speed_KBps": 182476.411,
    "speed_MBps": 178.200
  }
,
  {
    "request_num": 68,
    "payload":     "1mb.bin",
    "attempt":     28,
    "protocol":    "QUIC/HTTP3",
    "size_bytes":  1048635,
    "time_connect_s":  0.000470,
    "time_ttfb_s":     0.000260,
    "time_ttlb_s":     0.003680,
    "time_total_s":    0.006,
    "speed_Bps":  183681030,
    "speed_KBps": 179376.006,
    "speed_MBps": 175.172
  }
,
  {
    "request_num": 69,
    "payload":     "1mb.bin",
    "attempt":     29,
    "protocol":    "QUIC/HTTP3",
    "size_bytes":  1048635,
    "time_connect_s":  0.000450,
    "time_ttfb_s":     0.000250,
    "time_ttlb_s":     0.003400,
    "time_total_s":    0.005,
    "speed_Bps":  193904401,
    "speed_KBps": 189359.767,
    "speed_MBps": 184.922
  }
,
  {
    "request_num": 70,
    "payload":     "1mb.bin",
    "attempt":     30,
    "protocol":    "QUIC/HTTP3",
    "size_bytes":  1048635,
    "time_connect_s":  0.000450,
    "time_ttfb_s":     0.000250,
    "time_ttlb_s":     0.003720,
    "time_total_s":    0.006,
    "speed_Bps":  181928348,
    "speed_KBps": 177664.402,
    "speed_MBps": 173.500
  }
,
  {
    "request_num": 71,
    "payload":     "1mb.bin",
    "attempt":     31,
    "protocol":    "QUIC/HTTP3",
    "size_bytes":  1048635,
    "time_connect_s":  0.000440,
    "time_ttfb_s":     0.000270,
    "time_ttlb_s":     0.003750,
    "time_total_s":    0.006,
    "speed_Bps":  180830316,
    "speed_KBps": 176592.105,
    "speed_MBps": 172.453
  }
,
  {
    "request_num": 72,
    "payload":     "1mb.bin",
    "attempt":     32,
    "protocol":    "QUIC/HTTP3",
    "size_bytes":  1048635,
    "time_connect_s":  0.000430,
    "time_ttfb_s":     0.000260,
    "time_ttlb_s":     0.002780,
    "time_total_s":    0.005,
    "speed_Bps":  219977974,
    "speed_KBps": 214822.240,
    "speed_MBps": 209.787
  }
,
  {
    "request_num": 73,
    "payload":     "1mb.bin",
    "attempt":     33,
    "protocol":    "QUIC/HTTP3",
    "size_bytes":  1048635,
    "time_connect_s":  0.000460,
    "time_ttfb_s":     0.000260,
    "time_ttlb_s":     0.003580,
    "time_total_s":    0.006,
    "speed_Bps":  186225360,
    "speed_KBps": 181860.703,
    "speed_MBps": 177.598
  }
,
  {
    "request_num": 74,
    "payload":     "1mb.bin",
    "attempt":     34,
    "protocol":    "QUIC/HTTP3",
    "size_bytes":  1048635,
    "time_connect_s":  0.000440,
    "time_ttfb_s":     0.000270,
    "time_ttlb_s":     0.003560,
    "time_total_s":    0.006,
    "speed_Bps":  187893747,
    "speed_KBps": 183489.987,
    "speed_MBps": 179.189
  }
,
  {
    "request_num": 75,
    "payload":     "1mb.bin",
    "attempt":     35,
    "protocol":    "QUIC/HTTP3",
    "size_bytes":  1048635,
    "time_connect_s":  0.000450,
    "time_ttfb_s":     0.000260,
    "time_ttlb_s":     0.003490,
    "time_total_s":    0.005,
    "speed_Bps":  190973411,
    "speed_KBps": 186497.472,
    "speed_MBps": 182.126
  }
,
  {
    "request_num": 76,
    "payload":     "1mb.bin",
    "attempt":     36,
    "protocol":    "QUIC/HTTP3",
    "size_bytes":  1048635,
    "time_connect_s":  0.000440,
    "time_ttfb_s":     0.000260,
    "time_ttlb_s":     0.003290,
    "time_total_s":    0.005,
    "speed_Bps":  197297272,
    "speed_KBps": 192673.117,
    "speed_MBps": 188.157
  }
,
  {
    "request_num": 77,
    "payload":     "1mb.bin",
    "attempt":     37,
    "protocol":    "QUIC/HTTP3",
    "size_bytes":  1048635,
    "time_connect_s":  0.000450,
    "time_ttfb_s":     0.000280,
    "time_ttlb_s":     0.003720,
    "time_total_s":    0.006,
    "speed_Bps":  182023086,
    "speed_KBps": 177756.920,
    "speed_MBps": 173.591
  }
,
  {
    "request_num": 78,
    "payload":     "1mb.bin",
    "attempt":     38,
    "protocol":    "QUIC/HTTP3",
    "size_bytes":  1048635,
    "time_connect_s":  0.000450,
    "time_ttfb_s":     0.000280,
    "time_ttlb_s":     0.003400,
    "time_total_s":    0.005,
    "speed_Bps":  192692944,
    "speed_KBps": 188176.703,
    "speed_MBps": 183.766
  }
,
  {
    "request_num": 79,
    "payload":     "1mb.bin",
    "attempt":     39,
    "protocol":    "QUIC/HTTP3",
    "size_bytes":  1048635,
    "time_connect_s":  0.000420,
    "time_ttfb_s":     0.000330,
    "time_ttlb_s":     0.003240,
    "time_total_s":    0.005,
    "speed_Bps":  196006542,
    "speed_KBps": 191412.639,
    "speed_MBps": 186.926
  }
,
  {
    "request_num": 80,
    "payload":     "1mb.bin",
    "attempt":     40,
    "protocol":    "QUIC/HTTP3",
    "size_bytes":  1048635,
    "time_connect_s":  0.000450,
    "time_ttfb_s":     0.000250,
    "time_ttlb_s":     0.003090,
    "time_total_s":    0.005,
    "speed_Bps":  204014591,
    "speed_KBps": 199232.999,
    "speed_MBps": 194.563
  }
,
  {
    "request_num": 81,
    "payload":     "5mb.bin",
    "attempt":     1,
    "protocol":    "QUIC/HTTP3",
    "size_bytes":  5242939,
    "time_connect_s":  0.000440,
    "time_ttfb_s":     0.000750,
    "time_ttlb_s":     0.012190,
    "time_total_s":    0.015,
    "speed_Bps":  356274735,
    "speed_KBps": 347924.546,
    "speed_MBps": 339.770
  }
,
  {
    "request_num": 82,
    "payload":     "5mb.bin",
    "attempt":     2,
    "protocol":    "QUIC/HTTP3",
    "size_bytes":  5242939,
    "time_connect_s":  0.000430,
    "time_ttfb_s":     0.000380,
    "time_ttlb_s":     0.025880,
    "time_total_s":    0.028,
    "speed_Bps":  187034068,
    "speed_KBps": 182650.457,
    "speed_MBps": 178.370
  }
,
  {
    "request_num": 83,
    "payload":     "5mb.bin",
    "attempt":     3,
    "protocol":    "QUIC/HTTP3",
    "size_bytes":  5242939,
    "time_connect_s":  0.000440,
    "time_ttfb_s":     0.000250,
    "time_ttlb_s":     0.014590,
    "time_total_s":    0.017,
    "speed_Bps":  316507033,
    "speed_KBps": 309088.899,
    "speed_MBps": 301.845
  }
,
  {
    "request_num": 84,
    "payload":     "5mb.bin",
    "attempt":     4,
    "protocol":    "QUIC/HTTP3",
    "size_bytes":  5242939,
    "time_connect_s":  0.000440,
    "time_ttfb_s":     0.000270,
    "time_ttlb_s":     0.012320,
    "time_total_s":    0.014,
    "speed_Bps":  365743913,
    "speed_KBps": 357171.790,
    "speed_MBps": 348.801
  }
,
  {
    "request_num": 85,
    "payload":     "5mb.bin",
    "attempt":     5,
    "protocol":    "QUIC/HTTP3",
    "size_bytes":  5242939,
    "time_connect_s":  0.000450,
    "time_ttfb_s":     0.000270,
    "time_ttlb_s":     0.013670,
    "time_total_s":    0.016,
    "speed_Bps":  333287076,
    "speed_KBps": 325475.660,
    "speed_MBps": 317.847
  }
,
  {
    "request_num": 86,
    "payload":     "5mb.bin",
    "attempt":     6,
    "protocol":    "QUIC/HTTP3",
    "size_bytes":  5242939,
    "time_connect_s":  0.000430,
    "time_ttfb_s":     0.000270,
    "time_ttlb_s":     0.013090,
    "time_total_s":    0.015,
    "speed_Bps":  347099570,
    "speed_KBps": 338964.424,
    "speed_MBps": 331.020
  }
,
  {
    "request_num": 87,
    "payload":     "5mb.bin",
    "attempt":     7,
    "protocol":    "QUIC/HTTP3",
    "size_bytes":  5242939,
    "time_connect_s":  0.000440,
    "time_ttfb_s":     0.000260,
    "time_ttlb_s":     0.013360,
    "time_total_s":    0.015,
    "speed_Bps":  341203892,
    "speed_KBps": 333206.926,
    "speed_MBps": 325.397
  }
,
  {
    "request_num": 88,
    "payload":     "5mb.bin",
    "attempt":     8,
    "protocol":    "QUIC/HTTP3",
    "size_bytes":  5242939,
    "time_connect_s":  0.000420,
    "time_ttfb_s":     0.000260,
    "time_ttlb_s":     0.027250,
    "time_total_s":    0.029,
    "speed_Bps":  179056009,
    "speed_KBps": 174859.384,
    "speed_MBps": 170.761
  }
,
  {
    "request_num": 89,
    "payload":     "5mb.bin",
    "attempt":     9,
    "protocol":    "QUIC/HTTP3",
    "size_bytes":  5242939,
    "time_connect_s":  0.000420,
    "time_ttfb_s":     0.000340,
    "time_ttlb_s":     0.013230,
    "time_total_s":    0.015,
    "speed_Bps":  339239016,
    "speed_KBps": 331288.102,
    "speed_MBps": 323.524
  }
,
  {
    "request_num": 90,
    "payload":     "5mb.bin",
    "attempt":     10,
    "protocol":    "QUIC/HTTP3",
    "size_bytes":  5242939,
    "time_connect_s":  0.000410,
    "time_ttfb_s":     0.000310,
    "time_ttlb_s":     0.013350,
    "time_total_s":    0.015,
    "speed_Bps":  340959810,
    "speed_KBps": 332968.564,
    "speed_MBps": 325.165
  }
,
  {
    "request_num": 91,
    "payload":     "5mb.bin",
    "attempt":     11,
    "protocol":    "QUIC/HTTP3",
    "size_bytes":  5242939,
    "time_connect_s":  0.000480,
    "time_ttfb_s":     0.000280,
    "time_ttlb_s":     0.013270,
    "time_total_s":    0.015,
    "speed_Bps":  341448323,
    "speed_KBps": 333445.628,
    "speed_MBps": 325.630
  }
,
  {
    "request_num": 92,
    "payload":     "5mb.bin",
    "attempt":     12,
    "protocol":    "QUIC/HTTP3",
    "size_bytes":  5242939,
    "time_connect_s":  0.000450,
    "time_ttfb_s":     0.000260,
    "time_ttlb_s":     0.015090,
    "time_total_s":    0.017,
    "speed_Bps":  306532916,
    "speed_KBps": 299348.551,
    "speed_MBps": 292.333
  }
,
  {
    "request_num": 93,
    "payload":     "5mb.bin",
    "attempt":     13,
    "protocol":    "QUIC/HTTP3",
    "size_bytes":  5242939,
    "time_connect_s":  0.000460,
    "time_ttfb_s":     0.000270,
    "time_ttlb_s":     0.013800,
    "time_total_s":    0.016,
    "speed_Bps":  330826540,
    "speed_KBps": 323072.793,
    "speed_MBps": 315.501
  }
,
  {
    "request_num": 94,
    "payload":     "5mb.bin",
    "attempt":     14,
    "protocol":    "QUIC/HTTP3",
    "size_bytes":  5242939,
    "time_connect_s":  0.000430,
    "time_ttfb_s":     0.000320,
    "time_ttlb_s":     0.012260,
    "time_total_s":    0.014,
    "speed_Bps":  365769429,
    "speed_KBps": 357196.708,
    "speed_MBps": 348.825
  }
,
  {
    "request_num": 95,
    "payload":     "5mb.bin",
    "attempt":     15,
    "protocol":    "QUIC/HTTP3",
    "size_bytes":  5242939,
    "time_connect_s":  0.000470,
    "time_ttfb_s":     0.000280,
    "time_ttlb_s":     0.011830,
    "time_total_s":    0.014,
    "speed_Bps":  377733357,
    "speed_KBps": 368880.231,
    "speed_MBps": 360.235
  }
,
  {
    "request_num": 96,
    "payload":     "5mb.bin",
    "attempt":     16,
    "protocol":    "QUIC/HTTP3",
    "size_bytes":  5242939,
    "time_connect_s":  0.000450,
    "time_ttfb_s":     0.000260,
    "time_ttlb_s":     0.014170,
    "time_total_s":    0.016,
    "speed_Bps":  323438556,
    "speed_KBps": 315857.965,
    "speed_MBps": 308.455
  }
,
  {
    "request_num": 97,
    "payload":     "5mb.bin",
    "attempt":     17,
    "protocol":    "QUIC/HTTP3",
    "size_bytes":  5242939,
    "time_connect_s":  0.000440,
    "time_ttfb_s":     0.000260,
    "time_ttlb_s":     0.013050,
    "time_total_s":    0.015,
    "speed_Bps":  347790315,
    "speed_KBps": 339638.979,
    "speed_MBps": 331.679
  }
,
  {
    "request_num": 98,
    "payload":     "5mb.bin",
    "attempt":     18,
    "protocol":    "QUIC/HTTP3",
    "size_bytes":  5242939,
    "time_connect_s":  0.000450,
    "time_ttfb_s":     0.000270,
    "time_ttlb_s":     0.013700,
    "time_total_s":    0.016,
    "speed_Bps":  333181177,
    "speed_KBps": 325372.243,
    "speed_MBps": 317.746
  }
,
  {
    "request_num": 99,
    "payload":     "5mb.bin",
    "attempt":     19,
    "protocol":    "QUIC/HTTP3",
    "size_bytes":  5242939,
    "time_connect_s":  0.000440,
    "time_ttfb_s":     0.000330,
    "time_ttlb_s":     0.012670,
    "time_total_s":    0.015,
    "speed_Bps":  355405301,
    "speed_KBps": 347075.489,
    "speed_MBps": 338.941
  }
,
  {
    "request_num": 100,
    "payload":     "5mb.bin",
    "attempt":     20,
    "protocol":    "QUIC/HTTP3",
    "size_bytes":  5242939,
    "time_connect_s":  0.000450,
    "time_ttfb_s":     0.000280,
    "time_ttlb_s":     0.014280,
    "time_total_s":    0.016,
    "speed_Bps":  321514626,
    "speed_KBps": 313979.127,
    "speed_MBps": 306.620
  }
,
  {
    "request_num": 101,
    "payload":     "5mb.bin",
    "attempt":     21,
    "protocol":    "QUIC/HTTP3",
    "size_bytes":  5242939,
    "time_connect_s":  0.000450,
    "time_ttfb_s":     0.000360,
    "time_ttlb_s":     0.015020,
    "time_total_s":    0.017,
    "speed_Bps":  305996206,
    "speed_KBps": 298824.420,
    "speed_MBps": 291.821
  }
,
  {
    "request_num": 102,
    "payload":     "5mb.bin",
    "attempt":     22,
    "protocol":    "QUIC/HTTP3",
    "size_bytes":  5242939,
    "time_connect_s":  0.000460,
    "time_ttfb_s":     0.000330,
    "time_ttlb_s":     0.015270,
    "time_total_s":    0.017,
    "speed_Bps":  301145261,
    "speed_KBps": 294087.169,
    "speed_MBps": 287.195
  }
,
  {
    "request_num": 103,
    "payload":     "5mb.bin",
    "attempt":     23,
    "protocol":    "QUIC/HTTP3",
    "size_bytes":  5242939,
    "time_connect_s":  0.000450,
    "time_ttfb_s":     0.000270,
    "time_ttlb_s":     0.014660,
    "time_total_s":    0.017,
    "speed_Bps":  314324880,
    "speed_KBps": 306957.891,
    "speed_MBps": 299.764
  }
,
  {
    "request_num": 104,
    "payload":     "5mb.bin",
    "attempt":     24,
    "protocol":    "QUIC/HTTP3",
    "size_bytes":  5242939,
    "time_connect_s":  0.000430,
    "time_ttfb_s":     0.000340,
    "time_ttlb_s":     0.013410,
    "time_total_s":    0.016,
    "speed_Bps":  338101438,
    "speed_KBps": 330177.186,
    "speed_MBps": 322.439
  }
,
  {
    "request_num": 105,
    "payload":     "5mb.bin",
    "attempt":     25,
    "protocol":    "QUIC/HTTP3",
    "size_bytes":  5242939,
    "time_connect_s":  0.000460,
    "time_ttfb_s":     0.000260,
    "time_ttlb_s":     0.014900,
    "time_total_s":    0.017,
    "speed_Bps":  309044444,
    "speed_KBps": 301801.215,
    "speed_MBps": 294.728
  }
,
  {
    "request_num": 106,
    "payload":     "5mb.bin",
    "attempt":     26,
    "protocol":    "QUIC/HTTP3",
    "size_bytes":  5242939,
    "time_connect_s":  0.000450,
    "time_ttfb_s":     0.000400,
    "time_ttlb_s":     0.015430,
    "time_total_s":    0.018,
    "speed_Bps":  298521836,
    "speed_KBps": 291525.230,
    "speed_MBps": 284.693
  }
,
  {
    "request_num": 107,
    "payload":     "5mb.bin",
    "attempt":     27,
    "protocol":    "QUIC/HTTP3",
    "size_bytes":  5242939,
    "time_connect_s":  0.000440,
    "time_ttfb_s":     0.000270,
    "time_ttlb_s":     0.013840,
    "time_total_s":    0.016,
    "speed_Bps":  330347111,
    "speed_KBps": 322604.601,
    "speed_MBps": 315.044
  }
,
  {
    "request_num": 108,
    "payload":     "5mb.bin",
    "attempt":     28,
    "protocol":    "QUIC/HTTP3",
    "size_bytes":  5242939,
    "time_connect_s":  0.000450,
    "time_ttfb_s":     0.000260,
    "time_ttlb_s":     0.014290,
    "time_total_s":    0.016,
    "speed_Bps":  321042128,
    "speed_KBps": 313517.703,
    "speed_MBps": 306.170
  }
,
  {
    "request_num": 109,
    "payload":     "5mb.bin",
    "attempt":     29,
    "protocol":    "QUIC/HTTP3",
    "size_bytes":  5242939,
    "time_connect_s":  0.000420,
    "time_ttfb_s":     0.000290,
    "time_ttlb_s":     0.012270,
    "time_total_s":    0.014,
    "speed_Bps":  366639091,
    "speed_KBps": 358045.987,
    "speed_MBps": 349.654
  }
,
  {
    "request_num": 110,
    "payload":     "5mb.bin",
    "attempt":     30,
    "protocol":    "QUIC/HTTP3",
    "size_bytes":  5242939,
    "time_connect_s":  0.000460,
    "time_ttfb_s":     0.000360,
    "time_ttlb_s":     0.012890,
    "time_total_s":    0.015,
    "speed_Bps":  347099570,
    "speed_KBps": 338964.424,
    "speed_MBps": 331.020
  }
,
  {
    "request_num": 111,
    "payload":     "5mb.bin",
    "attempt":     31,
    "protocol":    "QUIC/HTTP3",
    "size_bytes":  5242939,
    "time_connect_s":  0.000420,
    "time_ttfb_s":     0.000230,
    "time_ttlb_s":     0.011450,
    "time_total_s":    0.013,
    "speed_Bps":  391176528,
    "speed_KBps": 382008.328,
    "speed_MBps": 373.055
  }
,
  {
    "request_num": 112,
    "payload":     "5mb.bin",
    "attempt":     32,
    "protocol":    "QUIC/HTTP3",
    "size_bytes":  5242939,
    "time_connect_s":  0.000390,
    "time_ttfb_s":     0.000240,
    "time_ttlb_s":     0.010970,
    "time_total_s":    0.013,
    "speed_Bps":  406429380,
    "speed_KBps": 396903.691,
    "speed_MBps": 387.601
  }
,
  {
    "request_num": 113,
    "payload":     "5mb.bin",
    "attempt":     33,
    "protocol":    "QUIC/HTTP3",
    "size_bytes":  5242939,
    "time_connect_s":  0.000430,
    "time_ttfb_s":     0.000240,
    "time_ttlb_s":     0.011190,
    "time_total_s":    0.013,
    "speed_Bps":  397704544,
    "speed_KBps": 388383.344,
    "speed_MBps": 379.281
  }
,
  {
    "request_num": 114,
    "payload":     "5mb.bin",
    "attempt":     34,
    "protocol":    "QUIC/HTTP3",
    "size_bytes":  5242939,
    "time_connect_s":  0.000390,
    "time_ttfb_s":     0.000220,
    "time_ttlb_s":     0.011300,
    "time_total_s":    0.013,
    "speed_Bps":  396741506,
    "speed_KBps": 387442.877,
    "speed_MBps": 378.362
  }
,
  {
    "request_num": 115,
    "payload":     "5mb.bin",
    "attempt":     35,
    "protocol":    "QUIC/HTTP3",
    "size_bytes":  5242939,
    "time_connect_s":  0.000410,
    "time_ttfb_s":     0.000310,
    "time_ttlb_s":     0.011980,
    "time_total_s":    0.014,
    "speed_Bps":  373774791,
    "speed_KBps": 365014.444,
    "speed_MBps": 356.459
  }
,
  {
    "request_num": 116,
    "payload":     "5mb.bin",
    "attempt":     36,
    "protocol":    "QUIC/HTTP3",
    "size_bytes":  5242939,
    "time_connect_s":  0.000430,
    "time_ttfb_s":     0.000330,
    "time_ttlb_s":     0.010500,
    "time_total_s":    0.013,
    "speed_Bps":  417364990,
    "speed_KBps": 407582.998,
    "speed_MBps": 398.030
  }
,
  {
    "request_num": 117,
    "payload":     "5mb.bin",
    "attempt":     37,
    "protocol":    "QUIC/HTTP3",
    "size_bytes":  5242939,
    "time_connect_s":  0.000460,
    "time_ttfb_s":     0.000340,
    "time_ttlb_s":     0.012900,
    "time_total_s":    0.015,
    "speed_Bps":  349063848,
    "speed_KBps": 340882.664,
    "speed_MBps": 332.893
  }
,
  {
    "request_num": 118,
    "payload":     "5mb.bin",
    "attempt":     38,
    "protocol":    "QUIC/HTTP3",
    "size_bytes":  5242939,
    "time_connect_s":  0.000420,
    "time_ttfb_s":     0.000340,
    "time_ttlb_s":     0.012980,
    "time_total_s":    0.015,
    "speed_Bps":  348506980,
    "speed_KBps": 340338.848,
    "speed_MBps": 332.362
  }
,
  {
    "request_num": 119,
    "payload":     "5mb.bin",
    "attempt":     39,
    "protocol":    "QUIC/HTTP3",
    "size_bytes":  5242939,
    "time_connect_s":  0.000440,
    "time_ttfb_s":     0.000370,
    "time_ttlb_s":     0.012680,
    "time_total_s":    0.015,
    "speed_Bps":  354180842,
    "speed_KBps": 345879.729,
    "speed_MBps": 337.773
  }
,
  {
    "request_num": 120,
    "payload":     "5mb.bin",
    "attempt":     40,
    "protocol":    "QUIC/HTTP3",
    "size_bytes":  5242939,
    "time_connect_s":  0.000440,
    "time_ttfb_s":     0.000250,
    "time_ttlb_s":     0.015020,
    "time_total_s":    0.017,
    "speed_Bps":  307449657,
    "speed_KBps": 300243.806,
    "speed_MBps": 293.207
  }
,
  {
    "request_num": 121,
    "payload":     "small_page.bin",
    "attempt":     1,
    "protocol":    "QUIC/HTTP3",
    "size_bytes":  20539,
    "time_connect_s":  0.000460,
    "time_ttfb_s":     0.000950,
    "time_ttlb_s":     0.000010,
    "time_total_s":    0.003,
    "speed_Bps":  7504202,
    "speed_KBps": 7328.322,
    "speed_MBps": 7.157
  }
,
  {
    "request_num": 122,
    "payload":     "small_page.bin",
    "attempt":     2,
    "protocol":    "QUIC/HTTP3",
    "size_bytes":  20539,
    "time_connect_s":  0.000510,
    "time_ttfb_s":     0.000250,
    "time_ttlb_s":     0.000040,
    "time_total_s":    0.002,
    "speed_Bps":  9734123,
    "speed_KBps": 9505.979,
    "speed_MBps": 9.283
  }
,
  {
    "request_num": 123,
    "payload":     "small_page.bin",
    "attempt":     3,
    "protocol":    "QUIC/HTTP3",
    "size_bytes":  20539,
    "time_connect_s":  0.000440,
    "time_ttfb_s":     0.000290,
    "time_ttlb_s":     0.000010,
    "time_total_s":    0.002,
    "speed_Bps":  10063204,
    "speed_KBps": 9827.348,
    "speed_MBps": 9.597
  }
,
  {
    "request_num": 124,
    "payload":     "small_page.bin",
    "attempt":     4,
    "protocol":    "QUIC/HTTP3",
    "size_bytes":  20539,
    "time_connect_s":  0.000440,
    "time_ttfb_s":     0.000290,
    "time_ttlb_s":     0.000010,
    "time_total_s":    0.002,
    "speed_Bps":  9780476,
    "speed_KBps": 9551.246,
    "speed_MBps": 9.327
  }
,
  {
    "request_num": 125,
    "payload":     "small_page.bin",
    "attempt":     5,
    "protocol":    "QUIC/HTTP3",
    "size_bytes":  20539,
    "time_connect_s":  0.000450,
    "time_ttfb_s":     0.000300,
    "time_ttlb_s":     0.000010,
    "time_total_s":    0.002,
    "speed_Bps":  10019024,
    "speed_KBps": 9784.203,
    "speed_MBps": 9.555
  }
,
  {
    "request_num": 126,
    "payload":     "small_page.bin",
    "attempt":     6,
    "protocol":    "QUIC/HTTP3",
    "size_bytes":  20539,
    "time_connect_s":  0.000420,
    "time_ttfb_s":     0.000250,
    "time_ttlb_s":     0.000010,
    "time_total_s":    0.002,
    "speed_Bps":  10254119,
    "speed_KBps": 10013.788,
    "speed_MBps": 9.779
  }
,
  {
    "request_num": 127,
    "payload":     "small_page.bin",
    "attempt":     7,
    "protocol":    "QUIC/HTTP3",
    "size_bytes":  20539,
    "time_connect_s":  0.000450,
    "time_ttfb_s":     0.000290,
    "time_ttlb_s":     0.000010,
    "time_total_s":    0.002,
    "speed_Bps":  9903086,
    "speed_KBps": 9670.982,
    "speed_MBps": 9.444
  }
,
  {
    "request_num": 128,
    "payload":     "small_page.bin",
    "attempt":     8,
    "protocol":    "QUIC/HTTP3",
    "size_bytes":  20539,
    "time_connect_s":  0.000440,
    "time_ttfb_s":     0.000310,
    "time_ttlb_s":     0.000010,
    "time_total_s":    0.002,
    "speed_Bps":  9975231,
    "speed_KBps": 9741.437,
    "speed_MBps": 9.513
  }
,
  {
    "request_num": 129,
    "payload":     "small_page.bin",
    "attempt":     9,
    "protocol":    "QUIC/HTTP3",
    "size_bytes":  20539,
    "time_connect_s":  0.000450,
    "time_ttfb_s":     0.000290,
    "time_ttlb_s":     0.000010,
    "time_total_s":    0.002,
    "speed_Bps":  10078018,
    "speed_KBps": 9841.814,
    "speed_MBps": 9.611
  }
,
  {
    "request_num": 130,
    "payload":     "small_page.bin",
    "attempt":     10,
    "protocol":    "QUIC/HTTP3",
    "size_bytes":  20539,
    "time_connect_s":  0.000450,
    "time_ttfb_s":     0.000240,
    "time_ttlb_s":     0.000050,
    "time_total_s":    0.002,
    "speed_Bps":  10087917,
    "speed_KBps": 9851.481,
    "speed_MBps": 9.621
  }
,
  {
    "request_num": 131,
    "payload":     "small_page.bin",
    "attempt":     11,
    "protocol":    "QUIC/HTTP3",
    "size_bytes":  20539,
    "time_connect_s":  0.000460,
    "time_ttfb_s":     0.000240,
    "time_ttlb_s":     0.000040,
    "time_total_s":    0.002,
    "speed_Bps":  9846117,
    "speed_KBps": 9615.349,
    "speed_MBps": 9.390
  }
,
  {
    "request_num": 132,
    "payload":     "small_page.bin",
    "attempt":     12,
    "protocol":    "QUIC/HTTP3",
    "size_bytes":  20539,
    "time_connect_s":  0.000470,
    "time_ttfb_s":     0.000310,
    "time_ttlb_s":     0.000010,
    "time_total_s":    0.002,
    "speed_Bps":  9865034,
    "speed_KBps": 9633.822,
    "speed_MBps": 9.408
  }
,
  {
    "request_num": 133,
    "payload":     "small_page.bin",
    "attempt":     13,
    "protocol":    "QUIC/HTTP3",
    "size_bytes":  20539,
    "time_connect_s":  0.000440,
    "time_ttfb_s":     0.000290,
    "time_ttlb_s":     0.000010,
    "time_total_s":    0.002,
    "speed_Bps":  10019024,
    "speed_KBps": 9784.203,
    "speed_MBps": 9.555
  }
,
  {
    "request_num": 134,
    "payload":     "small_page.bin",
    "attempt":     14,
    "protocol":    "QUIC/HTTP3",
    "size_bytes":  20539,
    "time_connect_s":  0.000460,
    "time_ttfb_s":     0.000300,
    "time_ttlb_s":     0.000010,
    "time_total_s":    0.002,
    "speed_Bps":  9789800,
    "speed_KBps": 9560.352,
    "speed_MBps": 9.336
  }
,
  {
    "request_num": 135,
    "payload":     "small_page.bin",
    "attempt":     15,
    "protocol":    "QUIC/HTTP3",
    "size_bytes":  20539,
    "time_connect_s":  0.000450,
    "time_ttfb_s":     0.000290,
    "time_ttlb_s":     0.000010,
    "time_total_s":    0.002,
    "speed_Bps":  10177899,
    "speed_KBps": 9939.354,
    "speed_MBps": 9.706
  }
,
  {
    "request_num": 136,
    "payload":     "small_page.bin",
    "attempt":     16,
    "protocol":    "QUIC/HTTP3",
    "size_bytes":  20539,
    "time_connect_s":  0.000450,
    "time_ttfb_s":     0.000230,
    "time_ttlb_s":     0.000040,
    "time_total_s":    0.002,
    "speed_Bps":  9850839,
    "speed_KBps": 9619.960,
    "speed_MBps": 9.394
  }
,
  {
    "request_num": 137,
    "payload":     "small_page.bin",
    "attempt":     17,
    "protocol":    "QUIC/HTTP3",
    "size_bytes":  20539,
    "time_connect_s":  0.000450,
    "time_ttfb_s":     0.000280,
    "time_ttlb_s":     0.000010,
    "time_total_s":    0.002,
    "speed_Bps":  10033708,
    "speed_KBps": 9798.543,
    "speed_MBps": 9.569
  }
,
  {
    "request_num": 138,
    "payload":     "small_page.bin",
    "attempt":     18,
    "protocol":    "QUIC/HTTP3",
    "size_bytes":  20539,
    "time_connect_s":  0.000420,
    "time_ttfb_s":     0.000240,
    "time_ttlb_s":     0.000010,
    "time_total_s":    0.002,
    "speed_Bps":  10208250,
    "speed_KBps": 9968.994,
    "speed_MBps": 9.735
  }
,
  {
    "request_num": 139,
    "payload":     "small_page.bin",
    "attempt":     19,
    "protocol":    "QUIC/HTTP3",
    "size_bytes":  20539,
    "time_connect_s":  0.000460,
    "time_ttfb_s":     0.000260,
    "time_ttlb_s":     0.000040,
    "time_total_s":    0.002,
    "speed_Bps":  9922222,
    "speed_KBps": 9689.670,
    "speed_MBps": 9.463
  }
,
  {
    "request_num": 140,
    "payload":     "small_page.bin",
    "attempt":     20,
    "protocol":    "QUIC/HTTP3",
    "size_bytes":  20539,
    "time_connect_s":  0.000460,
    "time_ttfb_s":     0.000300,
    "time_ttlb_s":     0.000010,
    "time_total_s":    0.002,
    "speed_Bps":  9711111,
    "speed_KBps": 9483.507,
    "speed_MBps": 9.261
  }
,
  {
    "request_num": 141,
    "payload":     "small_page.bin",
    "attempt":     21,
    "protocol":    "QUIC/HTTP3",
    "size_bytes":  20539,
    "time_connect_s":  0.000430,
    "time_ttfb_s":     0.000260,
    "time_ttlb_s":     0.000010,
    "time_total_s":    0.002,
    "speed_Bps":  10300401,
    "speed_KBps": 10058.985,
    "speed_MBps": 9.823
  }
,
  {
    "request_num": 142,
    "payload":     "small_page.bin",
    "attempt":     22,
    "protocol":    "QUIC/HTTP3",
    "size_bytes":  20539,
    "time_connect_s":  0.000440,
    "time_ttfb_s":     0.000250,
    "time_ttlb_s":     0.000010,
    "time_total_s":    0.002,
    "speed_Bps":  9941433,
    "speed_KBps": 9708.431,
    "speed_MBps": 9.481
  }
,
  {
    "request_num": 143,
    "payload":     "small_page.bin",
    "attempt":     23,
    "protocol":    "QUIC/HTTP3",
    "size_bytes":  20539,
    "time_connect_s":  0.000440,
    "time_ttfb_s":     0.000290,
    "time_ttlb_s":     0.000010,
    "time_total_s":    0.002,
    "speed_Bps":  10132708,
    "speed_KBps": 9895.223,
    "speed_MBps": 9.663
  }
,
  {
    "request_num": 144,
    "payload":     "small_page.bin",
    "attempt":     24,
    "protocol":    "QUIC/HTTP3",
    "size_bytes":  20539,
    "time_connect_s":  0.000430,
    "time_ttfb_s":     0.000300,
    "time_ttlb_s":     0.000010,
    "time_total_s":    0.002,
    "speed_Bps":  10048434,
    "speed_KBps": 9812.924,
    "speed_MBps": 9.583
  }
,
  {
    "request_num": 145,
    "payload":     "small_page.bin",
    "attempt":     25,
    "protocol":    "QUIC/HTTP3",
    "size_bytes":  20539,
    "time_connect_s":  0.000410,
    "time_ttfb_s":     0.000240,
    "time_ttlb_s":     0.000010,
    "time_total_s":    0.002,
    "speed_Bps":  10305569,
    "speed_KBps": 10064.032,
    "speed_MBps": 9.828
  }
,
  {
    "request_num": 146,
    "payload":     "small_page.bin",
    "attempt":     26,
    "protocol":    "QUIC/HTTP3",
    "size_bytes":  20539,
    "time_connect_s":  0.000460,
    "time_ttfb_s":     0.000290,
    "time_ttlb_s":     0.000010,
    "time_total_s":    0.002,
    "speed_Bps":  9999513,
    "speed_KBps": 9765.149,
    "speed_MBps": 9.536
  }
,
  {
    "request_num": 147,
    "payload":     "small_page.bin",
    "attempt":     27,
    "protocol":    "QUIC/HTTP3",
    "size_bytes":  20539,
    "time_connect_s":  0.000430,
    "time_ttfb_s":     0.000280,
    "time_ttlb_s":     0.000010,
    "time_total_s":    0.002,
    "speed_Bps":  10102804,
    "speed_KBps": 9866.020,
    "speed_MBps": 9.635
  }
,
  {
    "request_num": 148,
    "payload":     "small_page.bin",
    "attempt":     28,
    "protocol":    "QUIC/HTTP3",
    "size_bytes":  20539,
    "time_connect_s":  0.000430,
    "time_ttfb_s":     0.000290,
    "time_ttlb_s":     0.000010,
    "time_total_s":    0.002,
    "speed_Bps":  10122721,
    "speed_KBps": 9885.470,
    "speed_MBps": 9.654
  }
,
  {
    "request_num": 149,
    "payload":     "small_page.bin",
    "attempt":     29,
    "protocol":    "QUIC/HTTP3",
    "size_bytes":  20539,
    "time_connect_s":  0.000430,
    "time_ttfb_s":     0.000270,
    "time_ttlb_s":     0.000010,
    "time_total_s":    0.002,
    "speed_Bps":  10269500,
    "speed_KBps": 10028.809,
    "speed_MBps": 9.794
  }
,
  {
    "request_num": 150,
    "payload":     "small_page.bin",
    "attempt":     30,
    "protocol":    "QUIC/HTTP3",
    "size_bytes":  20539,
    "time_connect_s":  0.000450,
    "time_ttfb_s":     0.000300,
    "time_ttlb_s":     0.000010,
    "time_total_s":    0.002,
    "speed_Bps":  9701937,
    "speed_KBps": 9474.548,
    "speed_MBps": 9.252
  }
,
  {
    "request_num": 151,
    "payload":     "small_page.bin",
    "attempt":     31,
    "protocol":    "QUIC/HTTP3",
    "size_bytes":  20539,
    "time_connect_s":  0.000440,
    "time_ttfb_s":     0.000290,
    "time_ttlb_s":     0.000010,
    "time_total_s":    0.002,
    "speed_Bps":  10087917,
    "speed_KBps": 9851.481,
    "speed_MBps": 9.621
  }
,
  {
    "request_num": 152,
    "payload":     "small_page.bin",
    "attempt":     32,
    "protocol":    "QUIC/HTTP3",
    "size_bytes":  20539,
    "time_connect_s":  0.000450,
    "time_ttfb_s":     0.000290,
    "time_ttlb_s":     0.000010,
    "time_total_s":    0.002,
    "speed_Bps":  9888782,
    "speed_KBps": 9657.014,
    "speed_MBps": 9.431
  }
,
  {
    "request_num": 153,
    "payload":     "small_page.bin",
    "attempt":     33,
    "protocol":    "QUIC/HTTP3",
    "size_bytes":  20539,
    "time_connect_s":  0.000420,
    "time_ttfb_s":     0.000280,
    "time_ttlb_s":     0.000010,
    "time_total_s":    0.002,
    "speed_Bps":  10284927,
    "speed_KBps": 10043.874,
    "speed_MBps": 9.808
  }
,
  {
    "request_num": 154,
    "payload":     "small_page.bin",
    "attempt":     34,
    "protocol":    "QUIC/HTTP3",
    "size_bytes":  20539,
    "time_connect_s":  0.000440,
    "time_ttfb_s":     0.000290,
    "time_ttlb_s":     0.000010,
    "time_total_s":    0.002,
    "speed_Bps":  10068137,
    "speed_KBps": 9832.165,
    "speed_MBps": 9.602
  }
,
  {
    "request_num": 155,
    "payload":     "small_page.bin",
    "attempt":     35,
    "protocol":    "QUIC/HTTP3",
    "size_bytes":  20539,
    "time_connect_s":  0.000470,
    "time_ttfb_s":     0.000320,
    "time_ttlb_s":     0.000010,
    "time_total_s":    0.002,
    "speed_Bps":  9893545,
    "speed_KBps": 9661.665,
    "speed_MBps": 9.435
  }
,
  {
    "request_num": 156,
    "payload":     "small_page.bin",
    "attempt":     36,
    "protocol":    "QUIC/HTTP3",
    "size_bytes":  20539,
    "time_connect_s":  0.000450,
    "time_ttfb_s":     0.000290,
    "time_ttlb_s":     0.000010,
    "time_total_s":    0.002,
    "speed_Bps":  9860298,
    "speed_KBps": 9629.197,
    "speed_MBps": 9.404
  }
,
  {
    "request_num": 157,
    "payload":     "small_page.bin",
    "attempt":     37,
    "protocol":    "QUIC/HTTP3",
    "size_bytes":  20539,
    "time_connect_s":  0.000420,
    "time_ttfb_s":     0.000260,
    "time_ttlb_s":     0.000010,
    "time_total_s":    0.002,
    "speed_Bps":  10102804,
    "speed_KBps": 9866.020,
    "speed_MBps": 9.635
  }
,
  {
    "request_num": 158,
    "payload":     "small_page.bin",
    "attempt":     38,
    "protocol":    "QUIC/HTTP3",
    "size_bytes":  20539,
    "time_connect_s":  0.000420,
    "time_ttfb_s":     0.000320,
    "time_ttlb_s":     0.000010,
    "time_total_s":    0.002,
    "speed_Bps":  10033708,
    "speed_KBps": 9798.543,
    "speed_MBps": 9.569
  }
,
  {
    "request_num": 159,
    "payload":     "small_page.bin",
    "attempt":     39,
    "protocol":    "QUIC/HTTP3",
    "size_bytes":  20539,
    "time_connect_s":  0.000410,
    "time_ttfb_s":     0.000240,
    "time_ttlb_s":     0.000010,
    "time_total_s":    0.002,
    "speed_Bps":  10603511,
    "speed_KBps": 10354.991,
    "speed_MBps": 10.112
  }
,
  {
    "request_num": 160,
    "payload":     "small_page.bin",
    "attempt":     40,
    "protocol":    "QUIC/HTTP3",
    "size_bytes":  20539,
    "time_connect_s":  0.000430,
    "time_ttfb_s":     0.000260,
    "time_ttlb_s":     0.000010,
    "time_total_s":    0.002,
    "speed_Bps":  10254119,
    "speed_KBps": 10013.788,
    "speed_MBps": 9.779
  }
,
  {
    "request_num": 161,
    "payload":     "medium_page.bin",
    "attempt":     1,
    "protocol":    "QUIC/HTTP3",
    "size_bytes":  204859,
    "time_connect_s":  0.000480,
    "time_ttfb_s":     0.000900,
    "time_ttlb_s":     0.000900,
    "time_total_s":    0.004,
    "speed_Bps":  56731930,
    "speed_KBps": 55402.275,
    "speed_MBps": 54.104
  }
,
  {
    "request_num": 162,
    "payload":     "medium_page.bin",
    "attempt":     2,
    "protocol":    "QUIC/HTTP3",
    "size_bytes":  204859,
    "time_connect_s":  0.000450,
    "time_ttfb_s":     0.000250,
    "time_ttlb_s":     0.000730,
    "time_total_s":    0.003,
    "speed_Bps":  75649557,
    "speed_KBps": 73876.521,
    "speed_MBps": 72.145
  }
,
  {
    "request_num": 163,
    "payload":     "medium_page.bin",
    "attempt":     3,
    "protocol":    "QUIC/HTTP3",
    "size_bytes":  204859,
    "time_connect_s":  0.000450,
    "time_ttfb_s":     0.000270,
    "time_ttlb_s":     0.000710,
    "time_total_s":    0.003,
    "speed_Bps":  74957556,
    "speed_KBps": 73200.738,
    "speed_MBps": 71.485
  }
,
  {
    "request_num": 164,
    "payload":     "medium_page.bin",
    "attempt":     4,
    "protocol":    "QUIC/HTTP3",
    "size_bytes":  204859,
    "time_connect_s":  0.000440,
    "time_ttfb_s":     0.000350,
    "time_ttlb_s":     0.000640,
    "time_total_s":    0.003,
    "speed_Bps":  74332003,
    "speed_KBps": 72589.847,
    "speed_MBps": 70.889
  }
,
  {
    "request_num": 165,
    "payload":     "medium_page.bin",
    "attempt":     5,
    "protocol":    "QUIC/HTTP3",
    "size_bytes":  204859,
    "time_connect_s":  0.000470,
    "time_ttfb_s":     0.000280,
    "time_ttlb_s":     0.000750,
    "time_total_s":    0.003,
    "speed_Bps":  73163929,
    "speed_KBps": 71449.149,
    "speed_MBps": 69.775
  }
,
  {
    "request_num": 166,
    "payload":     "medium_page.bin",
    "attempt":     6,
    "protocol":    "QUIC/HTTP3",
    "size_bytes":  204859,
    "time_connect_s":  0.000440,
    "time_ttfb_s":     0.000250,
    "time_ttlb_s":     0.000770,
    "time_total_s":    0.003,
    "speed_Bps":  72877624,
    "speed_KBps": 71169.555,
    "speed_MBps": 69.502
  }
,
  {
    "request_num": 167,
    "payload":     "medium_page.bin",
    "attempt":     7,
    "protocol":    "QUIC/HTTP3",
    "size_bytes":  204859,
    "time_connect_s":  0.000430,
    "time_ttfb_s":     0.000260,
    "time_ttlb_s":     0.000740,
    "time_total_s":    0.003,
    "speed_Bps":  74711524,
    "speed_KBps": 72960.473,
    "speed_MBps": 71.250
  }
,
  {
    "request_num": 168,
    "payload":     "medium_page.bin",
    "attempt":     8,
    "protocol":    "QUIC/HTTP3",
    "size_bytes":  204859,
    "time_connect_s":  0.000430,
    "time_ttfb_s":     0.000410,
    "time_ttlb_s":     0.000670,
    "time_total_s":    0.003,
    "speed_Bps":  73007484,
    "speed_KBps": 71296.371,
    "speed_MBps": 69.625
  }
,
  {
    "request_num": 169,
    "payload":     "medium_page.bin",
    "attempt":     9,
    "protocol":    "QUIC/HTTP3",
    "size_bytes":  204859,
    "time_connect_s":  0.000440,
    "time_ttfb_s":     0.000270,
    "time_ttlb_s":     0.000710,
    "time_total_s":    0.003,
    "speed_Bps":  75454512,
    "speed_KBps": 73686.047,
    "speed_MBps": 71.959
  }
,
  {
    "request_num": 170,
    "payload":     "medium_page.bin",
    "attempt":     10,
    "protocol":    "QUIC/HTTP3",
    "size_bytes":  204859,
    "time_connect_s":  0.000450,
    "time_ttfb_s":     0.000260,
    "time_ttlb_s":     0.000760,
    "time_total_s":    0.003,
    "speed_Bps":  73637311,
    "speed_KBps": 71911.437,
    "speed_MBps": 70.226
  }
,
  {
    "request_num": 171,
    "payload":     "medium_page.bin",
    "attempt":     11,
    "protocol":    "QUIC/HTTP3",
    "size_bytes":  204859,
    "time_connect_s":  0.000450,
    "time_ttfb_s":     0.000400,
    "time_ttlb_s":     0.000690,
    "time_total_s":    0.003,
    "speed_Bps":  71205770,
    "speed_KBps": 69536.885,
    "speed_MBps": 67.907
  }
,
  {
    "request_num": 172,
    "payload":     "medium_page.bin",
    "attempt":     12,
    "protocol":    "QUIC/HTTP3",
    "size_bytes":  204859,
    "time_connect_s":  0.000430,
    "time_ttfb_s":     0.000360,
    "time_ttlb_s":     0.000660,
    "time_total_s":    0.003,
    "speed_Bps":  74793355,
    "speed_KBps": 73040.386,
    "speed_MBps": 71.329
  }
,
  {
    "request_num": 173,
    "payload":     "medium_page.bin",
    "attempt":     13,
    "protocol":    "QUIC/HTTP3",
    "size_bytes":  204859,
    "time_connect_s":  0.000450,
    "time_ttfb_s":     0.000270,
    "time_ttlb_s":     0.000760,
    "time_total_s":    0.003,
    "speed_Bps":  73716805,
    "speed_KBps": 71989.067,
    "speed_MBps": 70.302
  }
,
  {
    "request_num": 174,
    "payload":     "medium_page.bin",
    "attempt":     14,
    "protocol":    "QUIC/HTTP3",
    "size_bytes":  204859,
    "time_connect_s":  0.000470,
    "time_ttfb_s":     0.000430,
    "time_ttlb_s":     0.000770,
    "time_total_s":    0.003,
    "speed_Bps":  68263579,
    "speed_KBps": 66663.651,
    "speed_MBps": 65.101
  }
,
  {
    "request_num": 175,
    "payload":     "medium_page.bin",
    "attempt":     15,
    "protocol":    "QUIC/HTTP3",
    "size_bytes":  204859,
    "time_connect_s":  0.000440,
    "time_ttfb_s":     0.000350,
    "time_ttlb_s":     0.000700,
    "time_total_s":    0.003,
    "speed_Bps":  73452492,
    "speed_KBps": 71730.949,
    "speed_MBps": 70.050
  }
,
  {
    "request_num": 176,
    "payload":     "medium_page.bin",
    "attempt":     16,
    "protocol":    "QUIC/HTTP3",
    "size_bytes":  204859,
    "time_connect_s":  0.000430,
    "time_ttfb_s":     0.000390,
    "time_ttlb_s":     0.000660,
    "time_total_s":    0.003,
    "speed_Bps":  72670805,
    "speed_KBps": 70967.583,
    "speed_MBps": 69.304
  }
,
  {
    "request_num": 177,
    "payload":     "medium_page.bin",
    "attempt":     17,
    "protocol":    "QUIC/HTTP3",
    "size_bytes":  204859,
    "time_connect_s":  0.000440,
    "time_ttfb_s":     0.000270,
    "time_ttlb_s":     0.000730,
    "time_total_s":    0.003,
    "speed_Bps":  74930139,
    "speed_KBps": 73173.964,
    "speed_MBps": 71.459
  }
,
  {
    "request_num": 178,
    "payload":     "medium_page.bin",
    "attempt":     18,
    "protocol":    "QUIC/HTTP3",
    "size_bytes":  204859,
    "time_connect_s":  0.000470,
    "time_ttfb_s":     0.000350,
    "time_ttlb_s":     0.000650,
    "time_total_s":    0.003,
    "speed_Bps":  74413004,
    "speed_KBps": 72668.949,
    "speed_MBps": 70.966
  }
,
  {
    "request_num": 179,
    "payload":     "medium_page.bin",
    "attempt":     19,
    "protocol":    "QUIC/HTTP3",
    "size_bytes":  204859,
    "time_connect_s":  0.000450,
    "time_ttfb_s":     0.000260,
    "time_ttlb_s":     0.000710,
    "time_total_s":    0.003,
    "speed_Bps":  74251178,
    "speed_KBps": 72510.916,
    "speed_MBps": 70.811
  }
,
  {
    "request_num": 180,
    "payload":     "medium_page.bin",
    "attempt":     20,
    "protocol":    "QUIC/HTTP3",
    "size_bytes":  204859,
    "time_connect_s":  0.000420,
    "time_ttfb_s":     0.000330,
    "time_ttlb_s":     0.000610,
    "time_total_s":    0.003,
    "speed_Bps":  75761464,
    "speed_KBps": 73985.805,
    "speed_MBps": 72.252
  }
,
  {
    "request_num": 181,
    "payload":     "medium_page.bin",
    "attempt":     21,
    "protocol":    "QUIC/HTTP3",
    "size_bytes":  204859,
    "time_connect_s":  0.000410,
    "time_ttfb_s":     0.000330,
    "time_ttlb_s":     0.000650,
    "time_total_s":    0.003,
    "speed_Bps":  76297579,
    "speed_KBps": 74509.354,
    "speed_MBps": 72.763
  }
,
  {
    "request_num": 182,
    "payload":     "medium_page.bin",
    "attempt":     22,
    "protocol":    "QUIC/HTTP3",
    "size_bytes":  204859,
    "time_connect_s":  0.000410,
    "time_ttfb_s":     0.000310,
    "time_ttlb_s":     0.000600,
    "time_total_s":    0.003,
    "speed_Bps":  77982109,
    "speed_KBps": 76154.403,
    "speed_MBps": 74.370
  }
,
  {
    "request_num": 183,
    "payload":     "medium_page.bin",
    "attempt":     23,
    "protocol":    "QUIC/HTTP3",
    "size_bytes":  204859,
    "time_connect_s":  0.000440,
    "time_ttfb_s":     0.000320,
    "time_ttlb_s":     0.000510,
    "time_total_s":    0.003,
    "speed_Bps":  80305370,
    "speed_KBps": 78423.213,
    "speed_MBps": 76.585
  }
,
  {
    "request_num": 184,
    "payload":     "medium_page.bin",
    "attempt":     24,
    "protocol":    "QUIC/HTTP3",
    "size_bytes":  204859,
    "time_connect_s":  0.000440,
    "time_ttfb_s":     0.000340,
    "time_ttlb_s":     0.000690,
    "time_total_s":    0.003,
    "speed_Bps":  73929628,
    "speed_KBps": 72196.902,
    "speed_MBps": 70.505
  }
,
  {
    "request_num": 185,
    "payload":     "medium_page.bin",
    "attempt":     25,
    "protocol":    "QUIC/HTTP3",
    "size_bytes":  204859,
    "time_connect_s":  0.000420,
    "time_ttfb_s":     0.000310,
    "time_ttlb_s":     0.000600,
    "time_total_s":    0.003,
    "speed_Bps":  76927901,
    "speed_KBps": 75124.903,
    "speed_MBps": 73.364
  }
,
  {
    "request_num": 186,
    "payload":     "medium_page.bin",
    "attempt":     26,
    "protocol":    "QUIC/HTTP3",
    "size_bytes":  204859,
    "time_connect_s":  0.000420,
    "time_ttfb_s":     0.000320,
    "time_ttlb_s":     0.000600,
    "time_total_s":    0.003,
    "speed_Bps":  77745351,
    "speed_KBps": 75923.194,
    "speed_MBps": 74.144
  }
,
  {
    "request_num": 187,
    "payload":     "medium_page.bin",
    "attempt":     27,
    "protocol":    "QUIC/HTTP3",
    "size_bytes":  204859,
    "time_connect_s":  0.000430,
    "time_ttfb_s":     0.000320,
    "time_ttlb_s":     0.000600,
    "time_total_s":    0.003,
    "speed_Bps":  77392898,
    "speed_KBps": 75579.002,
    "speed_MBps": 73.808
  }
,
  {
    "request_num": 188,
    "payload":     "medium_page.bin",
    "attempt":     28,
    "protocol":    "QUIC/HTTP3",
    "size_bytes":  204859,
    "time_connect_s":  0.000460,
    "time_ttfb_s":     0.000340,
    "time_ttlb_s":     0.000580,
    "time_total_s":    0.003,
    "speed_Bps":  75649557,
    "speed_KBps": 73876.521,
    "speed_MBps": 72.145
  }
,
  {
    "request_num": 189,
    "payload":     "medium_page.bin",
    "attempt":     29,
    "protocol":    "QUIC/HTTP3",
    "size_bytes":  204859,
    "time_connect_s":  0.000410,
    "time_ttfb_s":     0.000330,
    "time_ttlb_s":     0.000610,
    "time_total_s":    0.003,
    "speed_Bps":  77539364,
    "speed_KBps": 75722.035,
    "speed_MBps": 73.947
  }
,
  {
    "request_num": 190,
    "payload":     "medium_page.bin",
    "attempt":     30,
    "protocol":    "QUIC/HTTP3",
    "size_bytes":  204859,
    "time_connect_s":  0.000460,
    "time_ttfb_s":     0.000380,
    "time_ttlb_s":     0.000690,
    "time_total_s":    0.003,
    "speed_Bps":  71629021,
    "speed_KBps": 69950.216,
    "speed_MBps": 68.311
  }
,
  {
    "request_num": 191,
    "payload":     "medium_page.bin",
    "attempt":     31,
    "protocol":    "QUIC/HTTP3",
    "size_bytes":  204859,
    "time_connect_s":  0.000410,
    "time_ttfb_s":     0.000320,
    "time_ttlb_s":     0.000610,
    "time_total_s":    0.003,
    "speed_Bps":  77804406,
    "speed_KBps": 75980.865,
    "speed_MBps": 74.200
  }
,
  {
    "request_num": 192,
    "payload":     "medium_page.bin",
    "attempt":     32,
    "protocol":    "QUIC/HTTP3",
    "size_bytes":  204859,
    "time_connect_s":  0.000460,
    "time_ttfb_s":     0.000400,
    "time_ttlb_s":     0.000770,
    "time_total_s":    0.003,
    "speed_Bps":  70253429,
    "speed_KBps": 68606.864,
    "speed_MBps": 66.999
  }
,
  {
    "request_num": 193,
    "payload":     "medium_page.bin",
    "attempt":     33,
    "protocol":    "QUIC/HTTP3",
    "size_bytes":  204859,
    "time_connect_s":  0.000420,
    "time_ttfb_s":     0.000340,
    "time_ttlb_s":     0.000680,
    "time_total_s":    0.003,
    "speed_Bps":  74278100,
    "speed_KBps": 72537.207,
    "speed_MBps": 70.837
  }
,
  {
    "request_num": 194,
    "payload":     "medium_page.bin",
    "attempt":     34,
    "protocol":    "QUIC/HTTP3",
    "size_bytes":  204859,
    "time_connect_s":  0.000440,
    "time_ttfb_s":     0.000250,
    "time_ttlb_s":     0.000660,
    "time_total_s":    0.003,
    "speed_Bps":  77804406,
    "speed_KBps": 75980.865,
    "speed_MBps": 74.200
  }
,
  {
    "request_num": 195,
    "payload":     "medium_page.bin",
    "attempt":     35,
    "protocol":    "QUIC/HTTP3",
    "size_bytes":  204859,
    "time_connect_s":  0.000450,
    "time_ttfb_s":     0.000280,
    "time_ttlb_s":     0.000750,
    "time_total_s":    0.003,
    "speed_Bps":  73373567,
    "speed_KBps": 71653.874,
    "speed_MBps": 69.974
  }
,
  {
    "request_num": 196,
    "payload":     "medium_page.bin",
    "attempt":     36,
    "protocol":    "QUIC/HTTP3",
    "size_bytes":  204859,
    "time_connect_s":  0.000460,
    "time_ttfb_s":     0.000250,
    "time_ttlb_s":     0.000690,
    "time_total_s":    0.003,
    "speed_Bps":  75067424,
    "speed_KBps": 73308.031,
    "speed_MBps": 71.590
  }
,
  {
    "request_num": 197,
    "payload":     "medium_page.bin",
    "attempt":     37,
    "protocol":    "QUIC/HTTP3",
    "size_bytes":  204859,
    "time_connect_s":  0.000420,
    "time_ttfb_s":     0.000320,
    "time_ttlb_s":     0.000620,
    "time_total_s":    0.003,
    "speed_Bps":  77568724,
    "speed_KBps": 75750.707,
    "speed_MBps": 73.975
  }
,
  {
    "request_num": 198,
    "payload":     "medium_page.bin",
    "attempt":     38,
    "protocol":    "QUIC/HTTP3",
    "size_bytes":  204859,
    "time_connect_s":  0.000430,
    "time_ttfb_s":     0.000250,
    "time_ttlb_s":     0.000490,
    "time_total_s":    0.002,
    "speed_Bps":  82338826,
    "speed_KBps": 80409.010,
    "speed_MBps": 78.524
  }
,
  {
    "request_num": 199,
    "payload":     "medium_page.bin",
    "attempt":     39,
    "protocol":    "QUIC/HTTP3",
    "size_bytes":  204859,
    "time_connect_s":  0.000460,
    "time_ttfb_s":     0.000280,
    "time_ttlb_s":     0.000730,
    "time_total_s":    0.003,
    "speed_Bps":  73085623,
    "speed_KBps": 71372.679,
    "speed_MBps": 69.700
  }
,
  {
    "request_num": 200,
    "payload":     "medium_page.bin",
    "attempt":     40,
    "protocol":    "QUIC/HTTP3",
    "size_bytes":  204859,
    "time_connect_s":  0.000450,
    "time_ttfb_s":     0.000290,
    "time_ttlb_s":     0.000590,
    "time_total_s":    0.003,
    "speed_Bps":  77072611,
    "speed_KBps": 75266.222,
    "speed_MBps": 73.502
  }
,
  {
    "request_num": 201,
    "payload":     "large_page.bin",
    "attempt":     1,
    "protocol":    "QUIC/HTTP3",
    "size_bytes":  512059,
    "time_connect_s":  0.000440,
    "time_ttfb_s":     0.000760,
    "time_ttlb_s":     0.001350,
    "time_total_s":    0.004,
    "speed_Bps":  132451888,
    "speed_KBps": 129347.547,
    "speed_MBps": 126.316
  }
,
  {
    "request_num": 202,
    "payload":     "large_page.bin",
    "attempt":     2,
    "protocol":    "QUIC/HTTP3",
    "size_bytes":  512059,
    "time_connect_s":  0.000430,
    "time_ttfb_s":     0.000350,
    "time_ttlb_s":     0.001640,
    "time_total_s":    0.004,
    "speed_Bps":  134469275,
    "speed_KBps": 131317.651,
    "speed_MBps": 128.240
  }
,
  {
    "request_num": 203,
    "payload":     "large_page.bin",
    "attempt":     3,
    "protocol":    "QUIC/HTTP3",
    "size_bytes":  512059,
    "time_connect_s":  0.000460,
    "time_ttfb_s":     0.000270,
    "time_ttlb_s":     0.001740,
    "time_total_s":    0.004,
    "speed_Bps":  136185904,
    "speed_KBps": 132994.047,
    "speed_MBps": 129.877
  }
,
  {
    "request_num": 204,
    "payload":     "large_page.bin",
    "attempt":     4,
    "protocol":    "QUIC/HTTP3",
    "size_bytes":  512059,
    "time_connect_s":  0.000460,
    "time_ttfb_s":     0.000400,
    "time_ttlb_s":     0.001810,
    "time_total_s":    0.004,
    "speed_Bps":  129047127,
    "speed_KBps": 126022.585,
    "speed_MBps": 123.069
  }
,
  {
    "request_num": 205,
    "payload":     "large_page.bin",
    "attempt":     5,
    "protocol":    "QUIC/HTTP3",
    "size_bytes":  512059,
    "time_connect_s":  0.000460,
    "time_ttfb_s":     0.000270,
    "time_ttlb_s":     0.001910,
    "time_total_s":    0.004,
    "speed_Bps":  128335589,
    "speed_KBps": 125327.724,
    "speed_MBps": 122.390
  }
,
  {
    "request_num": 206,
    "payload":     "large_page.bin",
    "attempt":     6,
    "protocol":    "QUIC/HTTP3",
    "size_bytes":  512059,
    "time_connect_s":  0.000450,
    "time_ttfb_s":     0.000390,
    "time_ttlb_s":     0.001740,
    "time_total_s":    0.004,
    "speed_Bps":  132178369,
    "speed_KBps": 129080.438,
    "speed_MBps": 126.055
  }
,
  {
    "request_num": 207,
    "payload":     "large_page.bin",
    "attempt":     7,
    "protocol":    "QUIC/HTTP3",
    "size_bytes":  512059,
    "time_connect_s":  0.000470,
    "time_ttfb_s":     0.000250,
    "time_ttlb_s":     0.001910,
    "time_total_s":    0.004,
    "speed_Bps":  130261765,
    "speed_KBps": 127208.755,
    "speed_MBps": 124.227
  }
,
  {
    "request_num": 208,
    "payload":     "large_page.bin",
    "attempt":     8,
    "protocol":    "QUIC/HTTP3",
    "size_bytes":  512059,
    "time_connect_s":  0.000450,
    "time_ttfb_s":     0.000270,
    "time_ttlb_s":     0.001840,
    "time_total_s":    0.004,
    "speed_Bps":  132349186,
    "speed_KBps": 129247.252,
    "speed_MBps": 126.218
  }
,
  {
    "request_num": 209,
    "payload":     "large_page.bin",
    "attempt":     9,
    "protocol":    "QUIC/HTTP3",
    "size_bytes":  512059,
    "time_connect_s":  0.000430,
    "time_ttfb_s":     0.000340,
    "time_ttlb_s":     0.001610,
    "time_total_s":    0.004,
    "speed_Bps":  139108666,
    "speed_KBps": 135848.307,
    "speed_MBps": 132.664
  }
,
  {
    "request_num": 210,
    "payload":     "large_page.bin",
    "attempt":     10,
    "protocol":    "QUIC/HTTP3",
    "size_bytes":  512059,
    "time_connect_s":  0.000470,
    "time_ttfb_s":     0.000250,
    "time_ttlb_s":     0.001890,
    "time_total_s":    0.004,
    "speed_Bps":  131129065,
    "speed_KBps": 128055.728,
    "speed_MBps": 125.054
  }
,
  {
    "request_num": 211,
    "payload":     "large_page.bin",
    "attempt":     11,
    "protocol":    "QUIC/HTTP3",
    "size_bytes":  512059,
    "time_connect_s":  0.000450,
    "time_ttfb_s":     0.000270,
    "time_ttlb_s":     0.001890,
    "time_total_s":    0.004,
    "speed_Bps":  130129352,
    "speed_KBps": 127079.445,
    "speed_MBps": 124.101
  }
,
  {
    "request_num": 212,
    "payload":     "large_page.bin",
    "attempt":     12,
    "protocol":    "QUIC/HTTP3",
    "size_bytes":  512059,
    "time_connect_s":  0.000430,
    "time_ttfb_s":     0.000270,
    "time_ttlb_s":     0.001840,
    "time_total_s":    0.004,
    "speed_Bps":  133175293,
    "speed_KBps": 130053.997,
    "speed_MBps": 127.006
  }
,
  {
    "request_num": 213,
    "payload":     "large_page.bin",
    "attempt":     13,
    "protocol":    "QUIC/HTTP3",
    "size_bytes":  512059,
    "time_connect_s":  0.000460,
    "time_ttfb_s":     0.000270,
    "time_ttlb_s":     0.001880,
    "time_total_s":    0.004,
    "speed_Bps":  129733722,
    "speed_KBps": 126693.088,
    "speed_MBps": 123.724
  }
,
  {
    "request_num": 214,
    "payload":     "large_page.bin",
    "attempt":     14,
    "protocol":    "QUIC/HTTP3",
    "size_bytes":  512059,
    "time_connect_s":  0.000460,
    "time_ttfb_s":     0.000280,
    "time_ttlb_s":     0.001900,
    "time_total_s":    0.004,
    "speed_Bps":  129865331,
    "speed_KBps": 126821.612,
    "speed_MBps": 123.849
  }
,
  {
    "request_num": 215,
    "payload":     "large_page.bin",
    "attempt":     15,
    "protocol":    "QUIC/HTTP3",
    "size_bytes":  512059,
    "time_connect_s":  0.000440,
    "time_ttfb_s":     0.000250,
    "time_ttlb_s":     0.001710,
    "time_total_s":    0.004,
    "speed_Bps":  138806994,
    "speed_KBps": 135553.705,
    "speed_MBps": 132.377
  }
,
  {
    "request_num": 216,
    "payload":     "large_page.bin",
    "attempt":     16,
    "protocol":    "QUIC/HTTP3",
    "size_bytes":  512059,
    "time_connect_s":  0.000460,
    "time_ttfb_s":     0.000270,
    "time_ttlb_s":     0.001840,
    "time_total_s":    0.004,
    "speed_Bps":  132042032,
    "speed_KBps": 128947.297,
    "speed_MBps": 125.925
  }
,
  {
    "request_num": 217,
    "payload":     "large_page.bin",
    "attempt":     17,
    "protocol":    "QUIC/HTTP3",
    "size_bytes":  512059,
    "time_connect_s":  0.000460,
    "time_ttfb_s":     0.000280,
    "time_ttlb_s":     0.001860,
    "time_total_s":    0.004,
    "speed_Bps":  129766599,
    "speed_KBps": 126725.194,
    "speed_MBps": 123.755
  }
,
  {
    "request_num": 218,
    "payload":     "large_page.bin",
    "attempt":     18,
    "protocol":    "QUIC/HTTP3",
    "size_bytes":  512059,
    "time_connect_s":  0.000440,
    "time_ttfb_s":     0.000250,
    "time_ttlb_s":     0.001670,
    "time_total_s":    0.004,
    "speed_Bps":  140675549,
    "speed_KBps": 137378.466,
    "speed_MBps": 134.159
  }
,
  {
    "request_num": 219,
    "payload":     "large_page.bin",
    "attempt":     19,
    "protocol":    "QUIC/HTTP3",
    "size_bytes":  512059,
    "time_connect_s":  0.000460,
    "time_ttfb_s":     0.000270,
    "time_ttlb_s":     0.001680,
    "time_total_s":    0.004,
    "speed_Bps":  137576303,
    "speed_KBps": 134351.858,
    "speed_MBps": 131.203
  }
,
  {
    "request_num": 220,
    "payload":     "large_page.bin",
    "attempt":     20,
    "protocol":    "QUIC/HTTP3",
    "size_bytes":  512059,
    "time_connect_s":  0.000430,
    "time_ttfb_s":     0.000350,
    "time_ttlb_s":     0.001580,
    "time_total_s":    0.004,
    "speed_Bps":  140675549,
    "speed_KBps": 137378.466,
    "speed_MBps": 134.159
  }
,
  {
    "request_num": 221,
    "payload":     "large_page.bin",
    "attempt":     21,
    "protocol":    "QUIC/HTTP3",
    "size_bytes":  512059,
    "time_connect_s":  0.000450,
    "time_ttfb_s":     0.000280,
    "time_ttlb_s":     0.001890,
    "time_total_s":    0.004,
    "speed_Bps":  131028403,
    "speed_KBps": 127957.425,
    "speed_MBps": 124.958
  }
,
  {
    "request_num": 222,
    "payload":     "large_page.bin",
    "attempt":     22,
    "protocol":    "QUIC/HTTP3",
    "size_bytes":  512059,
    "time_connect_s":  0.000450,
    "time_ttfb_s":     0.000270,
    "time_ttlb_s":     0.001870,
    "time_total_s":    0.004,
    "speed_Bps":  129471302,
    "speed_KBps": 126436.818,
    "speed_MBps": 123.473
  }
,
  {
    "request_num": 223,
    "payload":     "large_page.bin",
    "attempt":     23,
    "protocol":    "QUIC/HTTP3",
    "size_bytes":  512059,
    "time_connect_s":  0.000460,
    "time_ttfb_s":     0.000280,
    "time_ttlb_s":     0.001660,
    "time_total_s":    0.004,
    "speed_Bps":  138656648,
    "speed_KBps": 135406.883,
    "speed_MBps": 132.233
  }
,
  {
    "request_num": 224,
    "payload":     "large_page.bin",
    "attempt":     24,
    "protocol":    "QUIC/HTTP3",
    "size_bytes":  512059,
    "time_connect_s":  0.000420,
    "time_ttfb_s":     0.000320,
    "time_ttlb_s":     0.001540,
    "time_total_s":    0.004,
    "speed_Bps":  142595099,
    "speed_KBps": 139253.026,
    "speed_MBps": 135.989
  }
,
  {
    "request_num": 225,
    "payload":     "large_page.bin",
    "attempt":     25,
    "protocol":    "QUIC/HTTP3",
    "size_bytes":  512059,
    "time_connect_s":  0.000460,
    "time_ttfb_s":     0.000270,
    "time_ttlb_s":     0.001630,
    "time_total_s":    0.004,
    "speed_Bps":  139449619,
    "speed_KBps": 136181.269,
    "speed_MBps": 132.990
  }
,
  {
    "request_num": 226,
    "payload":     "large_page.bin",
    "attempt":     26,
    "protocol":    "QUIC/HTTP3",
    "size_bytes":  512059,
    "time_connect_s":  0.000430,
    "time_ttfb_s":     0.000260,
    "time_ttlb_s":     0.001580,
    "time_total_s":    0.004,
    "speed_Bps":  143193233,
    "speed_KBps": 139837.142,
    "speed_MBps": 136.560
  }
,
  {
    "request_num": 227,
    "payload":     "large_page.bin",
    "attempt":     27,
    "protocol":    "QUIC/HTTP3",
    "size_bytes":  512059,
    "time_connect_s":  0.000460,
    "time_ttfb_s":     0.000270,
    "time_ttlb_s":     0.001860,
    "time_total_s":    0.004,
    "speed_Bps":  131905976,
    "speed_KBps": 128814.430,
    "speed_MBps": 125.795
  }
,
  {
    "request_num": 228,
    "payload":     "large_page.bin",
    "attempt":     28,
    "protocol":    "QUIC/HTTP3",
    "size_bytes":  512059,
    "time_connect_s":  0.000440,
    "time_ttfb_s":     0.000270,
    "time_ttlb_s":     0.001590,
    "time_total_s":    0.004,
    "speed_Bps":  141883901,
    "speed_KBps": 138558.497,
    "speed_MBps": 135.311
  }
,
  {
    "request_num": 229,
    "payload":     "large_page.bin",
    "attempt":     29,
    "protocol":    "QUIC/HTTP3",
    "size_bytes":  512059,
    "time_connect_s":  0.000450,
    "time_ttfb_s":     0.000260,
    "time_ttlb_s":     0.001880,
    "time_total_s":    0.004,
    "speed_Bps":  130328073,
    "speed_KBps": 127273.509,
    "speed_MBps": 124.291
  }
,
  {
    "request_num": 230,
    "payload":     "large_page.bin",
    "attempt":     30,
    "protocol":    "QUIC/HTTP3",
    "size_bytes":  512059,
    "time_connect_s":  0.000420,
    "time_ttfb_s":     0.000270,
    "time_ttlb_s":     0.001600,
    "time_total_s":    0.004,
    "speed_Bps":  144079629,
    "speed_KBps": 140702.763,
    "speed_MBps": 137.405
  }
,
  {
    "request_num": 231,
    "payload":     "large_page.bin",
    "attempt":     31,
    "protocol":    "QUIC/HTTP3",
    "size_bytes":  512059,
    "time_connect_s":  0.000410,
    "time_ttfb_s":     0.000370,
    "time_ttlb_s":     0.001690,
    "time_total_s":    0.004,
    "speed_Bps":  135644768,
    "speed_KBps": 132465.594,
    "speed_MBps": 129.361
  }
,
  {
    "request_num": 232,
    "payload":     "large_page.bin",
    "attempt":     32,
    "protocol":    "QUIC/HTTP3",
    "size_bytes":  512059,
    "time_connect_s":  0.000450,
    "time_ttfb_s":     0.000270,
    "time_ttlb_s":     0.001640,
    "time_total_s":    0.004,
    "speed_Bps":  136804435,
    "speed_KBps": 133598.081,
    "speed_MBps": 130.467
  }
,
  {
    "request_num": 233,
    "payload":     "large_page.bin",
    "attempt":     33,
    "protocol":    "QUIC/HTTP3",
    "size_bytes":  512059,
    "time_connect_s":  0.000450,
    "time_ttfb_s":     0.000270,
    "time_ttlb_s":     0.001820,
    "time_total_s":    0.004,
    "speed_Bps":  133002338,
    "speed_KBps": 129885.096,
    "speed_MBps": 126.841
  }
,
  {
    "request_num": 234,
    "payload":     "large_page.bin",
    "attempt":     34,
    "protocol":    "QUIC/HTTP3",
    "size_bytes":  512059,
    "time_connect_s":  0.000420,
    "time_ttfb_s":     0.000320,
    "time_ttlb_s":     0.001540,
    "time_total_s":    0.004,
    "speed_Bps":  143514294,
    "speed_KBps": 140150.678,
    "speed_MBps": 136.866
  }
,
  {
    "request_num": 235,
    "payload":     "large_page.bin",
    "attempt":     35,
    "protocol":    "QUIC/HTTP3",
    "size_bytes":  512059,
    "time_connect_s":  0.000470,
    "time_ttfb_s":     0.000270,
    "time_ttlb_s":     0.001870,
    "time_total_s":    0.004,
    "speed_Bps":  129307828,
    "speed_KBps": 126277.176,
    "speed_MBps": 123.318
  }
,
  {
    "request_num": 236,
    "payload":     "large_page.bin",
    "attempt":     36,
    "protocol":    "QUIC/HTTP3",
    "size_bytes":  512059,
    "time_connect_s":  0.000460,
    "time_ttfb_s":     0.000270,
    "time_ttlb_s":     0.001910,
    "time_total_s":    0.004,
    "speed_Bps":  129964213,
    "speed_KBps": 126918.177,
    "speed_MBps": 123.944
  }
,
  {
    "request_num": 237,
    "payload":     "large_page.bin",
    "attempt":     37,
    "protocol":    "QUIC/HTTP3",
    "size_bytes":  512059,
    "time_connect_s":  0.000430,
    "time_ttfb_s":     0.000280,
    "time_ttlb_s":     0.001890,
    "time_total_s":    0.004,
    "speed_Bps":  131330854,
    "speed_KBps": 128252.787,
    "speed_MBps": 125.247
  }
,
  {
    "request_num": 238,
    "payload":     "large_page.bin",
    "attempt":     38,
    "protocol":    "QUIC/HTTP3",
    "size_bytes":  512059,
    "time_connect_s":  0.000440,
    "time_ttfb_s":     0.000250,
    "time_ttlb_s":     0.001890,
    "time_total_s":    0.004,
    "speed_Bps":  130361253,
    "speed_KBps": 127305.911,
    "speed_MBps": 124.322
  }
,
  {
    "request_num": 239,
    "payload":     "large_page.bin",
    "attempt":     39,
    "protocol":    "QUIC/HTTP3",
    "size_bytes":  512059,
    "time_connect_s":  0.000480,
    "time_ttfb_s":     0.000290,
    "time_ttlb_s":     0.001590,
    "time_total_s":    0.004,
    "speed_Bps":  139449619,
    "speed_KBps": 136181.269,
    "speed_MBps": 132.990
  }
,
  {
    "request_num": 240,
    "payload":     "large_page.bin",
    "attempt":     40,
    "protocol":    "QUIC/HTTP3",
    "size_bytes":  512059,
    "time_connect_s":  0.000450,
    "time_ttfb_s":     0.000270,
    "time_ttlb_s":     0.001910,
    "time_total_s":    0.004,
    "speed_Bps":  130195525,
    "speed_KBps": 127144.067,
    "speed_MBps": 124.164
  }
]
